{
  "file_name": "FactoryGame/Content/FactoryGame/Interface/UI/Menu/Widget_MenuButton.uasset",
  "guid": {
    "a": 1647439519,
    "b": 1098244631,
    "c": 1491658376,
    "d": 2434222068
  },
  "exports": [
    {
      "name": "CallFunc_Add_IntInt_ReturnValue",
      "class": {
        "package": "/Script/CoreUObject",
        "name": "IntProperty"
      },
      "super": null,
      "template": {
        "package": "/Script/CoreUObject",
        "name": "Default__IntProperty"
      },
      "outer": {
        "package": "{{THIS PACKAGE}}",
        "name": "ExecuteUbergraph_Widget_MenuButton"
      },
      "properties": {}
    },
    {
      "name": "CallFunc_GetFactoryGameDarkGray_Graphics",
      "class": {
        "package": "/Script/CoreUObject",
        "name": "StructProperty"
      },
      "super": null,
      "template": {
        "package": "/Script/CoreUObject",
        "name": "Default__StructProperty"
      },
      "outer": {
        "package": "{{THIS PACKAGE}}",
        "name": "GetHoverColor"
      },
      "properties": {}
    },
    {
      "name": "K2Node_CreateDelegate_OutputDelegate",
      "class": {
        "package": "/Script/CoreUObject",
        "name": "DelegateProperty"
      },
      "super": null,
      "template": {
        "package": "/Script/CoreUObject",
        "name": "Default__DelegateProperty"
      },
      "outer": {
        "package": "{{THIS PACKAGE}}",
        "name": "ExecuteUbergraph_Widget_MenuButton"
      },
      "properties": {}
    },
    {
      "name": "CallFunc_GetFactoryGameWhite_TextWhite1",
      "class": {
        "package": "/Script/CoreUObject",
        "name": "StructProperty"
      },
      "super": null,
      "template": {
        "package": "/Script/CoreUObject",
        "name": "Default__StructProperty"
      },
      "outer": {
        "package": "{{THIS PACKAGE}}",
        "name": "GetButtonColor"
      },
      "properties": {}
    },
    {
      "name": "MyGeometry",
      "class": {
        "package": "/Script/CoreUObject",
        "name": "StructProperty"
      },
      "super": null,
      "template": {
        "package": "/Script/CoreUObject",
        "name": "Default__StructProperty"
      },
      "outer": {
        "package": "{{THIS PACKAGE}}",
        "name": "{{BROKEN/MISSING EXPORT}}"
      },
      "properties": {}
    },
    {
      "name": "CallFunc_IsHovered_ReturnValue",
      "class": {
        "package": "/Script/CoreUObject",
        "name": "BoolProperty"
      },
      "super": null,
      "template": {
        "package": "/Script/CoreUObject",
        "name": "Default__BoolProperty"
      },
      "outer": {
        "package": "{{THIS PACKAGE}}",
        "name": "GetHoverColor"
      },
      "properties": {}
    },
    {
      "name": "HorizontalBoxSlot",
      "class": {
        "package": "/Script/UMG",
        "name": "HorizontalBoxSlot"
      },
      "super": null,
      "template": {
        "package": "/Script/UMG",
        "name": "Default__HorizontalBoxSlot"
      },
      "outer": {
        "package": "{{THIS PACKAGE}}",
        "name": "HorizontalBox"
      },
      "properties": {
        "Content": {
          "type": "ObjectProperty",
          "value": {
            "type": "reference",
            "value": {
              "package": "{{THIS PACKAGE}}",
              "name": "Overlay"
            }
          }
        },
        "HorizontalAlignment": {
          "type": "ByteProperty",
          "value": "HAlign_Left"
        },
        "Parent": {
          "type": "ObjectProperty",
          "value": {
            "type": "reference",
            "value": {
              "package": "{{THIS PACKAGE}}",
              "name": "HorizontalBox"
            }
          }
        },
        "VerticalAlignment": {
          "type": "ByteProperty",
          "value": "VAlign_Top"
        }
      }
    },
    {
      "name": "Overlay",
      "class": {
        "package": "/Script/UMG",
        "name": "Overlay"
      },
      "super": null,
      "template": {
        "package": "/Script/UMG",
        "name": "Default__Overlay"
      },
      "outer": {
        "package": "{{THIS PACKAGE}}",
        "name": "{{BROKEN/MISSING EXPORT}}"
      },
      "properties": {
        "Slot": {
          "type": "ObjectProperty",
          "value": {
            "type": "reference",
            "value": {
              "package": "{{THIS PACKAGE}}",
              "name": "ButtonSlot"
            }
          }
        },
        "Slots": {
          "type": "ArrayProperty",
          "value": [
            {
              "type": "reference",
              "value": {
                "package": "{{THIS PACKAGE}}",
                "name": "OverlaySlot"
              }
            },
            {
              "type": "reference",
              "value": {
                "package": "{{THIS PACKAGE}}",
                "name": "OverlaySlot"
              }
            },
            {
              "type": "reference",
              "value": {
                "package": "{{THIS PACKAGE}}",
                "name": "OverlaySlot"
              }
            }
          ]
        }
      }
    },
    {
      "name": "Overlay",
      "class": {
        "package": "/Script/UMG",
        "name": "Overlay"
      },
      "super": null,
      "template": {
        "package": "/Script/UMG",
        "name": "Default__Overlay"
      },
      "outer": {
        "package": "{{THIS PACKAGE}}",
        "name": "{{BROKEN/MISSING EXPORT}}"
      },
      "properties": {
        "Slot": {
          "type": "ObjectProperty",
          "value": {
            "type": "reference",
            "value": {
              "package": "{{THIS PACKAGE}}",
              "name": "ButtonSlot"
            }
          }
        },
        "Slots": {
          "type": "ArrayProperty",
          "value": [
            {
              "type": "reference",
              "value": {
                "package": "{{THIS PACKAGE}}",
                "name": "OverlaySlot"
              }
            },
            {
              "type": "reference",
              "value": {
                "package": "{{THIS PACKAGE}}",
                "name": "OverlaySlot"
              }
            },
            {
              "type": "reference",
              "value": {
                "package": "{{THIS PACKAGE}}",
                "name": "OverlaySlot"
              }
            }
          ]
        }
      }
    },
    {
      "name": "CallFunc_GetFactoryGameOrange_OrangeText",
      "class": {
        "package": "/Script/CoreUObject",
        "name": "StructProperty"
      },
      "super": null,
      "template": {
        "package": "/Script/CoreUObject",
        "name": "Default__StructProperty"
      },
      "outer": {
        "package": "{{THIS PACKAGE}}",
        "name": "GetButtonColor"
      },
      "properties": {}
    },
    {
      "name": "CallFunc_GetFactoryGameOrange_Orange",
      "class": {
        "package": "/Script/CoreUObject",
        "name": "StructProperty"
      },
      "super": null,
      "template": {
        "package": "/Script/CoreUObject",
        "name": "Default__StructProperty"
      },
      "outer": {
        "package": "{{THIS PACKAGE}}",
        "name": "GetHoverColor"
      },
      "properties": {}
    },
    {
      "name": "CallFunc_Less_IntInt_ReturnValue",
      "class": {
        "package": "/Script/CoreUObject",
        "name": "BoolProperty"
      },
      "super": null,
      "template": {
        "package": "/Script/CoreUObject",
        "name": "Default__BoolProperty"
      },
      "outer": {
        "package": "{{THIS PACKAGE}}",
        "name": "ExecuteUbergraph_Widget_MenuButton"
      },
      "properties": {}
    },
    {
      "name": "Destruct",
      "class": {
        "package": "/Script/CoreUObject",
        "name": "Function"
      },
      "super": {
        "package": "UserWidget",
        "name": "Destruct"
      },
      "template": {
        "package": "/Script/CoreUObject",
        "name": "Default__Function"
      },
      "outer": {
        "package": "{{THIS PACKAGE}}",
        "name": "Widget_MenuButton_C"
      },
      "properties": {}
    },
    {
      "name": "ReturnValue",
      "class": {
        "package": "/Script/CoreUObject",
        "name": "StructProperty"
      },
      "super": null,
      "template": {
        "package": "/Script/CoreUObject",
        "name": "Default__StructProperty"
      },
      "outer": {
        "package": "{{THIS PACKAGE}}",
        "name": "{{BROKEN/MISSING EXPORT}}"
      },
      "properties": {}
    },
    {
      "name": "CallFunc_GetFactoryGameWhite_GraphicsWhite",
      "class": {
        "package": "/Script/CoreUObject",
        "name": "StructProperty"
      },
      "super": null,
      "template": {
        "package": "/Script/CoreUObject",
        "name": "Default__StructProperty"
      },
      "outer": {
        "package": "{{THIS PACKAGE}}",
        "name": "GetButtonColor"
      },
      "properties": {}
    },
    {
      "name": "HorizontalBoxSlot",
      "class": {
        "package": "/Script/UMG",
        "name": "HorizontalBoxSlot"
      },
      "super": null,
      "template": {
        "package": "/Script/UMG",
        "name": "Default__HorizontalBoxSlot"
      },
      "outer": {
        "package": "{{THIS PACKAGE}}",
        "name": "HorizontalBox"
      },
      "properties": {
        "Content": {
          "type": "ObjectProperty",
          "value": {
            "type": "reference",
            "value": {
              "package": "{{THIS PACKAGE}}",
              "name": "Overlay"
            }
          }
        },
        "HorizontalAlignment": {
          "type": "ByteProperty",
          "value": "HAlign_Left"
        },
        "Parent": {
          "type": "ObjectProperty",
          "value": {
            "type": "reference",
            "value": {
              "package": "{{THIS PACKAGE}}",
              "name": "HorizontalBox"
            }
          }
        },
        "VerticalAlignment": {
          "type": "ByteProperty",
          "value": "VAlign_Top"
        }
      }
    },
    {
      "name": "Overlay",
      "class": {
        "package": "/Script/UMG",
        "name": "Overlay"
      },
      "super": null,
      "template": {
        "package": "/Script/UMG",
        "name": "Default__Overlay"
      },
      "outer": {
        "package": "{{THIS PACKAGE}}",
        "name": "{{BROKEN/MISSING EXPORT}}"
      },
      "properties": {
        "Slot": {
          "type": "ObjectProperty",
          "value": {
            "type": "reference",
            "value": {
              "package": "{{THIS PACKAGE}}",
              "name": "HorizontalBoxSlot"
            }
          }
        },
        "Slots": {
          "type": "ArrayProperty",
          "value": [
            {
              "type": "reference",
              "value": {
                "package": "{{THIS PACKAGE}}",
                "name": "OverlaySlot"
              }
            },
            {
              "type": "reference",
              "value": {
                "package": "{{THIS PACKAGE}}",
                "name": "OverlaySlot"
              }
            }
          ]
        }
      }
    },
    {
      "name": "CallFunc_GetAllWidgetsOfClassInHierarchy_foundWidgets",
      "class": {
        "package": "/Script/CoreUObject",
        "name": "ArrayProperty"
      },
      "super": null,
      "template": {
        "package": "/Script/CoreUObject",
        "name": "Default__ArrayProperty"
      },
      "outer": {
        "package": "{{THIS PACKAGE}}",
        "name": "ExecuteUbergraph_Widget_MenuButton"
      },
      "properties": {}
    },
    {
      "name": "GetHoverColor",
      "class": {
        "package": "/Script/CoreUObject",
        "name": "Function"
      },
      "super": null,
      "template": {
        "package": "/Script/CoreUObject",
        "name": "Default__Function"
      },
      "outer": {
        "package": "{{THIS PACKAGE}}",
        "name": "Widget_MenuButton_C"
      },
      "properties": {}
    },
    {
      "name": "CallFunc_GetOwningPlayer_ReturnValue",
      "class": {
        "package": "/Script/CoreUObject",
        "name": "ObjectProperty"
      },
      "super": null,
      "template": {
        "package": "/Script/CoreUObject",
        "name": "Default__ObjectProperty"
      },
      "outer": {
        "package": "{{THIS PACKAGE}}",
        "name": "{{BROKEN/MISSING EXPORT}}"
      },
      "properties": {}
    },
    {
      "name": "GetButtonColor",
      "class": {
        "package": "/Script/CoreUObject",
        "name": "Function"
      },
      "super": null,
      "template": {
        "package": "/Script/CoreUObject",
        "name": "Default__Function"
      },
      "outer": {
        "package": "{{THIS PACKAGE}}",
        "name": "Widget_MenuButton_C"
      },
      "properties": {}
    },
    {
      "name": "OnClickedAsTabSwitcher",
      "class": {
        "package": "/Script/CoreUObject",
        "name": "MulticastDelegateProperty"
      },
      "super": null,
      "template": {
        "package": "/Script/CoreUObject",
        "name": "Default__MulticastDelegateProperty"
      },
      "outer": {
        "package": "{{THIS PACKAGE}}",
        "name": "Widget_MenuButton_C"
      },
      "properties": {}
    },
    {
      "name": "CallFunc_GetParent_ReturnValue",
      "class": {
        "package": "/Script/CoreUObject",
        "name": "ObjectProperty"
      },
      "super": null,
      "template": {
        "package": "/Script/CoreUObject",
        "name": "Default__ObjectProperty"
      },
      "outer": {
        "package": "{{THIS PACKAGE}}",
        "name": "ExecuteUbergraph_Widget_MenuButton"
      },
      "properties": {}
    },
    {
      "name": "OverlaySlot",
      "class": {
        "package": "/Script/UMG",
        "name": "OverlaySlot"
      },
      "super": null,
      "template": {
        "package": "/Script/UMG",
        "name": "Default__OverlaySlot"
      },
      "outer": {
        "package": "{{THIS PACKAGE}}",
        "name": "Overlay"
      },
      "properties": {
        "Content": {
          "type": "ObjectProperty",
          "value": {
            "type": "reference",
            "value": {
              "package": "{{THIS PACKAGE}}",
              "name": "SizeBox"
            }
          }
        },
        "HorizontalAlignment": {
          "type": "ByteProperty",
          "value": "HAlign_Center"
        },
        "Parent": {
          "type": "ObjectProperty",
          "value": {
            "type": "reference",
            "value": {
              "package": "{{THIS PACKAGE}}",
              "name": "Overlay"
            }
          }
        },
        "VerticalAlignment": {
          "type": "ByteProperty",
          "value": "VAlign_Center"
        }
      }
    },
    {
      "name": "SizeBox",
      "class": {
        "package": "/Script/UMG",
        "name": "SizeBox"
      },
      "super": null,
      "template": {
        "package": "/Script/UMG",
        "name": "Default__SizeBox"
      },
      "outer": {
        "package": "{{THIS PACKAGE}}",
        "name": "{{BROKEN/MISSING EXPORT}}"
      },
      "properties": {
        "HeightOverride": {
          "type": "FloatProperty",
          "value": 26
        },
        "Slot": {
          "type": "ObjectProperty",
          "value": {
            "type": "reference",
            "value": {
              "package": "{{THIS PACKAGE}}",
              "name": "OverlaySlot"
            }
          }
        },
        "Slots": {
          "type": "ArrayProperty",
          "value": [
            {
              "type": "reference",
              "value": {
                "package": "{{THIS PACKAGE}}",
                "name": "SizeBoxSlot"
              }
            }
          ]
        },
        "WidthOverride": {
          "type": "FloatProperty",
          "value": 26
        },
        "bOverride_HeightOverride": {
          "type": "BoolProperty",
          "value": true
        },
        "bOverride_WidthOverride": {
          "type": "BoolProperty",
          "value": true
        }
      }
    },
    {
      "name": "Default__Widget_MenuButton_C",
      "class": {
        "package": "{{THIS PACKAGE}}",
        "name": "Widget_MenuButton_C"
      },
      "super": null,
      "template": {
        "package": "/Script/FactoryGame",
        "name": "Default__FGButtonWidget"
      },
      "outer": null,
      "properties": {
        "UberGraphFrame": {
          "type": "PointerToUberGraphFrame",
          "value": null
        },
        "bHasScriptImplementedPaint": {
          "type": "BoolProperty",
          "value": false
        },
        "bHasScriptImplementedTick": {
          "type": "BoolProperty",
          "value": false
        },
        "bIsFocusable": {
          "type": "BoolProperty",
          "value": true
        },
        "mBrush": {
          "type": "SlateBrush",
          "value": {
            "DrawAs": {
              "type": "ByteProperty",
              "value": "ESlateBrushDrawType::Image"
            },
            "ImageSize": {
              "type": "Vector2D",
              "value": {
                "x": 32,
                "y": 32
              }
            },
            "ImageType": {
              "type": "ByteProperty",
              "value": "ESlateBrushImageType::NoImage"
            },
            "Margin": {
              "type": "Margin",
              "value": {
                "Bottom": {
                  "type": "FloatProperty",
                  "value": 0
                },
                "Left": {
                  "type": "FloatProperty",
                  "value": 0
                },
                "Right": {
                  "type": "FloatProperty",
                  "value": 0
                },
                "Top": {
                  "type": "FloatProperty",
                  "value": 0
                }
              }
            },
            "Mirroring": {
              "type": "ByteProperty",
              "value": "ESlateBrushMirrorType::NoMirror"
            },
            "ResourceName": {
              "type": "NameProperty",
              "value": "None"
            },
            "ResourceObject": {
              "type": "ObjectProperty",
              "value": {
                "type": "reference",
                "value": null
              }
            },
            "Tiling": {
              "type": "ByteProperty",
              "value": "ESlateBrushTileType::NoTile"
            },
            "TintColor": {
              "type": "SlateColor",
              "value": {
                "ColorUseRule": {
                  "type": "ByteProperty",
                  "value": "ESlateColorStylingMode::UseColor_Specified"
                },
                "SpecifiedColor": {
                  "type": "LinearColor",
                  "value": {
                    "r": 1,
                    "g": 1,
                    "b": 1,
                    "a": 1
                  }
                }
              }
            },
            "UVRegion": {
              "type": "Box2D",
              "value": {
                "is_valid": 0,
                "min": {
                  "x": 0,
                  "y": 0
                },
                "max": {
                  "x": 0,
                  "y": 0
                }
              }
            },
            "bIsDynamicallyLoaded": {
              "type": "BoolProperty",
              "value": false
            }
          }
        }
      }
    },
    {
      "name": "BndEvt__Button_0_K2Node_ComponentBoundEvent_0_OnButtonClickedEvent__DelegateSignature",
      "class": {
        "package": "/Script/CoreUObject",
        "name": "Function"
      },
      "super": null,
      "template": {
        "package": "/Script/CoreUObject",
        "name": "Default__Function"
      },
      "outer": {
        "package": "{{THIS PACKAGE}}",
        "name": "Widget_MenuButton_C"
      },
      "properties": {}
    },
    {
      "name": "CallFunc_GetFactoryGameWhite_TextWhite",
      "class": {
        "package": "/Script/CoreUObject",
        "name": "StructProperty"
      },
      "super": null,
      "template": {
        "package": "/Script/CoreUObject",
        "name": "Default__StructProperty"
      },
      "outer": {
        "package": "{{THIS PACKAGE}}",
        "name": "GetButtonColor"
      },
      "properties": {}
    },
    {
      "name": "OverlaySlot",
      "class": {
        "package": "/Script/UMG",
        "name": "OverlaySlot"
      },
      "super": null,
      "template": {
        "package": "/Script/UMG",
        "name": "Default__OverlaySlot"
      },
      "outer": {
        "package": "{{THIS PACKAGE}}",
        "name": "Overlay"
      },
      "properties": {
        "Content": {
          "type": "ObjectProperty",
          "value": {
            "type": "reference",
            "value": {
              "package": "{{THIS PACKAGE}}",
              "name": "buttonSize"
            }
          }
        },
        "HorizontalAlignment": {
          "type": "ByteProperty",
          "value": "HAlign_Fill"
        },
        "Parent": {
          "type": "ObjectProperty",
          "value": {
            "type": "reference",
            "value": {
              "package": "{{THIS PACKAGE}}",
              "name": "Overlay"
            }
          }
        },
        "VerticalAlignment": {
          "type": "ByteProperty",
          "value": "VAlign_Fill"
        }
      }
    },
    {
      "name": "ButtonText",
      "class": {
        "package": "/Script/UMG",
        "name": "TextBlock"
      },
      "super": null,
      "template": {
        "package": "/Script/UMG",
        "name": "Default__TextBlock"
      },
      "outer": {
        "package": "{{THIS PACKAGE}}",
        "name": "{{BROKEN/MISSING EXPORT}}"
      },
      "properties": {
        "ColorAndOpacity": {
          "type": "SlateColor",
          "value": {
            "SpecifiedColor": {
              "type": "LinearColor",
              "value": {
                "r": 0.132868,
                "g": 0.132868,
                "b": 0.135633,
                "a": 1
              }
            }
          }
        },
        "Font": {
          "type": "SlateFontInfo",
          "value": {
            "FontObject": {
              "type": "ObjectProperty",
              "value": {
                "type": "reference",
                "value": {
                  "package": "/Game/FactoryGame/Interface/Font/DescriptionText",
                  "name": "DescriptionText"
                }
              }
            },
            "Size": {
              "type": "IntProperty",
              "value": 14
            },
            "TypefaceFontName": {
              "type": "NameProperty",
              "value": "Default"
            }
          }
        },
        "Slot": {
          "type": "ObjectProperty",
          "value": {
            "type": "reference",
            "value": {
              "package": "{{THIS PACKAGE}}",
              "name": "HorizontalBoxSlot"
            }
          }
        },
        "Text": {
          "type": "TextProperty",
          "value": {
            "flags": 0,
            "history_type": 0,
            "namespace": "",
            "key": "54A49EFF4CAA78C592A256A2E2E5DE71",
            "source_string": "Text Block"
          }
        }
      }
    },
    {
      "name": "HorizontalBoxSlot",
      "class": {
        "package": "/Script/UMG",
        "name": "HorizontalBoxSlot"
      },
      "super": null,
      "template": {
        "package": "/Script/UMG",
        "name": "Default__HorizontalBoxSlot"
      },
      "outer": {
        "package": "{{THIS PACKAGE}}",
        "name": "HorizontalBox"
      },
      "properties": {
        "Content": {
          "type": "ObjectProperty",
          "value": {
            "type": "reference",
            "value": {
              "package": "{{THIS PACKAGE}}",
              "name": "ButtonText"
            }
          }
        },
        "Padding": {
          "type": "Margin",
          "value": {
            "Left": {
              "type": "FloatProperty",
              "value": 10
            }
          }
        },
        "Parent": {
          "type": "ObjectProperty",
          "value": {
            "type": "reference",
            "value": {
              "package": "{{THIS PACKAGE}}",
              "name": "HorizontalBox"
            }
          }
        },
        "Size": {
          "type": "SlateChildSize",
          "value": {
            "SizeRule": {
              "type": "ByteProperty",
              "value": "ESlateSizeRule::Fill"
            }
          }
        },
        "VerticalAlignment": {
          "type": "ByteProperty",
          "value": "VAlign_Center"
        }
      }
    },
    {
      "name": "mOptionsIcon",
      "class": {
        "package": "/Script/UMG",
        "name": "Image"
      },
      "super": null,
      "template": {
        "package": "/Script/UMG",
        "name": "Default__Image"
      },
      "outer": {
        "package": "{{THIS PACKAGE}}",
        "name": "{{BROKEN/MISSING EXPORT}}"
      },
      "properties": {
        "Brush": {
          "type": "SlateBrush",
          "value": {
            "ImageSize": {
              "type": "Vector2D",
              "value": {
                "x": 94,
                "y": 94
              }
            },
            "ResourceObject": {
              "type": "ObjectProperty",
              "value": {
                "type": "reference",
                "value": {
                  "package": "/Game/FactoryGame/Interface/UI/Menu/Graphics/Options_Controls",
                  "name": "Options_Controls"
                }
              }
            }
          }
        },
        "Slot": {
          "type": "ObjectProperty",
          "value": {
            "type": "reference",
            "value": {
              "package": "{{THIS PACKAGE}}",
              "name": "SizeBoxSlot"
            }
          }
        }
      }
    },
    {
      "name": "CallFunc_GetFactoryGameDarkGray_Text",
      "class": {
        "package": "/Script/CoreUObject",
        "name": "StructProperty"
      },
      "super": null,
      "template": {
        "package": "/Script/CoreUObject",
        "name": "Default__StructProperty"
      },
      "outer": {
        "package": "{{THIS PACKAGE}}",
        "name": "GetButtonColor"
      },
      "properties": {}
    },
    {
      "name": "CallFunc_GetFactoryGameOrange_Orange",
      "class": {
        "package": "/Script/CoreUObject",
        "name": "StructProperty"
      },
      "super": null,
      "template": {
        "package": "/Script/CoreUObject",
        "name": "Default__StructProperty"
      },
      "outer": {
        "package": "{{THIS PACKAGE}}",
        "name": "GetButtonColor"
      },
      "properties": {}
    },
    {
      "name": "OnClicked__DelegateSignature",
      "class": {
        "package": "/Script/CoreUObject",
        "name": "Function"
      },
      "super": null,
      "template": {
        "package": "/Script/CoreUObject",
        "name": "Default__Function"
      },
      "outer": {
        "package": "{{THIS PACKAGE}}",
        "name": "Widget_MenuButton_C"
      },
      "properties": {}
    },
    {
      "name": "OverlaySlot",
      "class": {
        "package": "/Script/UMG",
        "name": "OverlaySlot"
      },
      "super": null,
      "template": {
        "package": "/Script/UMG",
        "name": "Default__OverlaySlot"
      },
      "outer": {
        "package": "{{THIS PACKAGE}}",
        "name": "Overlay"
      },
      "properties": {
        "Content": {
          "type": "ObjectProperty",
          "value": {
            "type": "reference",
            "value": {
              "package": "{{THIS PACKAGE}}",
              "name": "HorizontalBox"
            }
          }
        },
        "HorizontalAlignment": {
          "type": "ByteProperty",
          "value": "HAlign_Fill"
        },
        "Padding": {
          "type": "Margin",
          "value": {
            "Bottom": {
              "type": "FloatProperty",
              "value": 4
            },
            "Left": {
              "type": "FloatProperty",
              "value": 30
            },
            "Right": {
              "type": "FloatProperty",
              "value": 4
            },
            "Top": {
              "type": "FloatProperty",
              "value": 4
            }
          }
        },
        "Parent": {
          "type": "ObjectProperty",
          "value": {
            "type": "reference",
            "value": {
              "package": "{{THIS PACKAGE}}",
              "name": "Overlay"
            }
          }
        }
      }
    },
    {
      "name": "CallFunc_GetFactoryGameWhite_TextWhite",
      "class": {
        "package": "/Script/CoreUObject",
        "name": "StructProperty"
      },
      "super": null,
      "template": {
        "package": "/Script/CoreUObject",
        "name": "Default__StructProperty"
      },
      "outer": {
        "package": "{{THIS PACKAGE}}",
        "name": "GetHoverColor"
      },
      "properties": {}
    },
    {
      "name": "CallFunc_IsValid_ReturnValue",
      "class": {
        "package": "/Script/CoreUObject",
        "name": "BoolProperty"
      },
      "super": null,
      "template": {
        "package": "/Script/CoreUObject",
        "name": "Default__BoolProperty"
      },
      "outer": {
        "package": "{{THIS PACKAGE}}",
        "name": "ExecuteUbergraph_Widget_MenuButton"
      },
      "properties": {}
    },
    {
      "name": "CallFunc_GetFactoryGameDarkGray_Text",
      "class": {
        "package": "/Script/CoreUObject",
        "name": "StructProperty"
      },
      "super": null,
      "template": {
        "package": "/Script/CoreUObject",
        "name": "Default__StructProperty"
      },
      "outer": {
        "package": "{{THIS PACKAGE}}",
        "name": "GetHoverColor"
      },
      "properties": {}
    },
    {
      "name": "ComponentDelegateBinding",
      "class": {
        "package": "/Script/Engine",
        "name": "ComponentDelegateBinding"
      },
      "super": null,
      "template": {
        "package": "/Script/Engine",
        "name": "Default__ComponentDelegateBinding"
      },
      "outer": {
        "package": "{{THIS PACKAGE}}",
        "name": "Widget_MenuButton_C"
      },
      "properties": {
        "ComponentDelegateBindings": {
          "type": "ArrayProperty",
          "value": [
            {
              "type": "BlueprintComponentDelegateBinding",
              "value": {
                "ComponentPropertyName": {
                  "type": "NameProperty",
                  "value": "MenuButton"
                },
                "DelegatePropertyName": {
                  "type": "NameProperty",
                  "value": "OnClicked"
                },
                "FunctionNameToBind": {
                  "type": "NameProperty",
                  "value": "BndEvt__Button_0_K2Node_ComponentBoundEvent_0_OnButtonClickedEvent__DelegateSignature"
                }
              }
            }
          ]
        }
      }
    },
    {
      "name": "CallFunc_Array_Get_Item",
      "class": {
        "package": "/Script/CoreUObject",
        "name": "ObjectProperty"
      },
      "super": null,
      "template": {
        "package": "/Script/CoreUObject",
        "name": "Default__ObjectProperty"
      },
      "outer": {
        "package": "{{THIS PACKAGE}}",
        "name": "ExecuteUbergraph_Widget_MenuButton"
      },
      "properties": {}
    },
    {
      "name": "OverlaySlot",
      "class": {
        "package": "/Script/UMG",
        "name": "OverlaySlot"
      },
      "super": null,
      "template": {
        "package": "/Script/UMG",
        "name": "Default__OverlaySlot"
      },
      "outer": {
        "package": "{{THIS PACKAGE}}",
        "name": "Overlay"
      },
      "properties": {
        "Content": {
          "type": "ObjectProperty",
          "value": {
            "type": "reference",
            "value": {
              "package": "{{THIS PACKAGE}}",
              "name": "SizeBox"
            }
          }
        },
        "HorizontalAlignment": {
          "type": "ByteProperty",
          "value": "HAlign_Center"
        },
        "Parent": {
          "type": "ObjectProperty",
          "value": {
            "type": "reference",
            "value": {
              "package": "{{THIS PACKAGE}}",
              "name": "Overlay"
            }
          }
        },
        "VerticalAlignment": {
          "type": "ByteProperty",
          "value": "VAlign_Center"
        }
      }
    },
    {
      "name": "UberGraphFrame",
      "class": {
        "package": "/Script/CoreUObject",
        "name": "StructProperty"
      },
      "super": null,
      "template": {
        "package": "/Script/CoreUObject",
        "name": "Default__StructProperty"
      },
      "outer": {
        "package": "{{THIS PACKAGE}}",
        "name": "{{BROKEN/MISSING EXPORT}}"
      },
      "properties": {}
    },
    {
      "name": "OnClickedAsTabSwitcher__DelegateSignature",
      "class": {
        "package": "/Script/CoreUObject",
        "name": "Function"
      },
      "super": null,
      "template": {
        "package": "/Script/CoreUObject",
        "name": "Default__Function"
      },
      "outer": {
        "package": "{{THIS PACKAGE}}",
        "name": "Widget_MenuButton_C"
      },
      "properties": {}
    },
    {
      "name": "ReturnValue",
      "class": {
        "package": "/Script/CoreUObject",
        "name": "StructProperty"
      },
      "super": null,
      "template": {
        "package": "/Script/CoreUObject",
        "name": "Default__StructProperty"
      },
      "outer": {
        "package": "{{THIS PACKAGE}}",
        "name": "{{BROKEN/MISSING EXPORT}}"
      },
      "properties": {}
    },
    {
      "name": "mOptionsIcon",
      "class": {
        "package": "/Script/CoreUObject",
        "name": "ObjectProperty"
      },
      "super": null,
      "template": {
        "package": "/Script/CoreUObject",
        "name": "Default__ObjectProperty"
      },
      "outer": {
        "package": "{{THIS PACKAGE}}",
        "name": "Widget_MenuButton_C"
      },
      "properties": {}
    },
    {
      "name": "HorizontalBox",
      "class": {
        "package": "/Script/UMG",
        "name": "HorizontalBox"
      },
      "super": null,
      "template": {
        "package": "/Script/UMG",
        "name": "Default__HorizontalBox"
      },
      "outer": {
        "package": "{{THIS PACKAGE}}",
        "name": "{{BROKEN/MISSING EXPORT}}"
      },
      "properties": {
        "Slot": {
          "type": "ObjectProperty",
          "value": {
            "type": "reference",
            "value": {
              "package": "{{THIS PACKAGE}}",
              "name": "OverlaySlot"
            }
          }
        },
        "Slots": {
          "type": "ArrayProperty",
          "value": [
            {
              "type": "reference",
              "value": {
                "package": "{{THIS PACKAGE}}",
                "name": "HorizontalBoxSlot"
              }
            },
            {
              "type": "reference",
              "value": {
                "package": "{{THIS PACKAGE}}",
                "name": "HorizontalBoxSlot"
              }
            }
          ]
        }
      }
    },
    {
      "name": "mOptionsIcon",
      "class": {
        "package": "/Script/UMG",
        "name": "Image"
      },
      "super": null,
      "template": {
        "package": "/Script/UMG",
        "name": "Default__Image"
      },
      "outer": {
        "package": "{{THIS PACKAGE}}",
        "name": "{{BROKEN/MISSING EXPORT}}"
      },
      "properties": {
        "Brush": {
          "type": "SlateBrush",
          "value": {
            "ImageSize": {
              "type": "Vector2D",
              "value": {
                "x": 94,
                "y": 94
              }
            },
            "ResourceObject": {
              "type": "ObjectProperty",
              "value": {
                "type": "reference",
                "value": {
                  "package": "/Game/FactoryGame/Interface/UI/Menu/Graphics/Options_Controls",
                  "name": "Options_Controls"
                }
              }
            }
          }
        },
        "Slot": {
          "type": "ObjectProperty",
          "value": {
            "type": "reference",
            "value": {
              "package": "{{THIS PACKAGE}}",
              "name": "SizeBoxSlot"
            }
          }
        }
      }
    },
    {
      "name": "CallFunc_GetAllWidgetsOfClassInHierarchy_foundWidgets",
      "class": {
        "package": "/Script/CoreUObject",
        "name": "ObjectProperty"
      },
      "super": null,
      "template": {
        "package": "/Script/CoreUObject",
        "name": "Default__ObjectProperty"
      },
      "outer": {
        "package": "{{THIS PACKAGE}}",
        "name": "{{BROKEN/MISSING EXPORT}}"
      },
      "properties": {}
    },
    {
      "name": "CallFunc_Not_PreBool_ReturnValue",
      "class": {
        "package": "/Script/CoreUObject",
        "name": "BoolProperty"
      },
      "super": null,
      "template": {
        "package": "/Script/CoreUObject",
        "name": "Default__BoolProperty"
      },
      "outer": {
        "package": "{{THIS PACKAGE}}",
        "name": "ExecuteUbergraph_Widget_MenuButton"
      },
      "properties": {}
    },
    {
      "name": "CallFunc_SelectColor_ReturnValue1",
      "class": {
        "package": "/Script/CoreUObject",
        "name": "StructProperty"
      },
      "super": null,
      "template": {
        "package": "/Script/CoreUObject",
        "name": "Default__StructProperty"
      },
      "outer": {
        "package": "{{THIS PACKAGE}}",
        "name": "GetHoverColor"
      },
      "properties": {}
    },
    {
      "name": "HorizontalBoxSlot",
      "class": {
        "package": "/Script/UMG",
        "name": "HorizontalBoxSlot"
      },
      "super": null,
      "template": {
        "package": "/Script/UMG",
        "name": "Default__HorizontalBoxSlot"
      },
      "outer": {
        "package": "{{THIS PACKAGE}}",
        "name": "HorizontalBox"
      },
      "properties": {
        "Content": {
          "type": "ObjectProperty",
          "value": {
            "type": "reference",
            "value": {
              "package": "{{THIS PACKAGE}}",
              "name": "ButtonText"
            }
          }
        },
        "Padding": {
          "type": "Margin",
          "value": {
            "Left": {
              "type": "FloatProperty",
              "value": 10
            }
          }
        },
        "Parent": {
          "type": "ObjectProperty",
          "value": {
            "type": "reference",
            "value": {
              "package": "{{THIS PACKAGE}}",
              "name": "HorizontalBox"
            }
          }
        },
        "Size": {
          "type": "SlateChildSize",
          "value": {
            "SizeRule": {
              "type": "ByteProperty",
              "value": "ESlateSizeRule::Fill"
            }
          }
        },
        "VerticalAlignment": {
          "type": "ByteProperty",
          "value": "VAlign_Center"
        }
      }
    },
    {
      "name": "OverlaySlot",
      "class": {
        "package": "/Script/UMG",
        "name": "OverlaySlot"
      },
      "super": null,
      "template": {
        "package": "/Script/UMG",
        "name": "Default__OverlaySlot"
      },
      "outer": {
        "package": "{{THIS PACKAGE}}",
        "name": "Overlay"
      },
      "properties": {
        "Content": {
          "type": "ObjectProperty",
          "value": {
            "type": "reference",
            "value": {
              "package": "{{THIS PACKAGE}}",
              "name": "HorizontalBox"
            }
          }
        },
        "HorizontalAlignment": {
          "type": "ByteProperty",
          "value": "HAlign_Fill"
        },
        "Padding": {
          "type": "Margin",
          "value": {
            "Bottom": {
              "type": "FloatProperty",
              "value": 4
            },
            "Left": {
              "type": "FloatProperty",
              "value": 30
            },
            "Right": {
              "type": "FloatProperty",
              "value": 4
            },
            "Top": {
              "type": "FloatProperty",
              "value": 4
            }
          }
        },
        "Parent": {
          "type": "ObjectProperty",
          "value": {
            "type": "reference",
            "value": {
              "package": "{{THIS PACKAGE}}",
              "name": "Overlay"
            }
          }
        }
      }
    },
    {
      "name": "mBrush",
      "class": {
        "package": "/Script/CoreUObject",
        "name": "StructProperty"
      },
      "super": null,
      "template": {
        "package": "/Script/CoreUObject",
        "name": "Default__StructProperty"
      },
      "outer": {
        "package": "{{THIS PACKAGE}}",
        "name": "Widget_MenuButton_C"
      },
      "properties": {}
    },
    {
      "name": "MenuButton",
      "class": {
        "package": "/Script/UMG",
        "name": "Button"
      },
      "super": null,
      "template": {
        "package": "/Script/UMG",
        "name": "Default__Button"
      },
      "outer": {
        "package": "{{THIS PACKAGE}}",
        "name": "{{BROKEN/MISSING EXPORT}}"
      },
      "properties": {
        "Slots": {
          "type": "ArrayProperty",
          "value": [
            {
              "type": "reference",
              "value": {
                "package": "{{THIS PACKAGE}}",
                "name": "ButtonSlot"
              }
            }
          ]
        },
        "WidgetStyle": {
          "type": "ButtonStyle",
          "value": {
            "Hovered": {
              "type": "SlateBrush",
              "value": {
                "DrawAs": {
                  "type": "ByteProperty",
                  "value": "ESlateBrushDrawType::NoDrawType"
                }
              }
            },
            "Normal": {
              "type": "SlateBrush",
              "value": {
                "DrawAs": {
                  "type": "ByteProperty",
                  "value": "ESlateBrushDrawType::NoDrawType"
                }
              }
            },
            "Pressed": {
              "type": "SlateBrush",
              "value": {
                "DrawAs": {
                  "type": "ByteProperty",
                  "value": "ESlateBrushDrawType::NoDrawType"
                }
              }
            },
            "PressedPadding": {
              "type": "Margin",
              "value": {
                "Bottom": {
                  "type": "FloatProperty",
                  "value": 2
                },
                "Top": {
                  "type": "FloatProperty",
                  "value": 2
                }
              }
            }
          }
        }
      }
    },
    {
      "name": "CallFunc_Array_Length_ReturnValue",
      "class": {
        "package": "/Script/CoreUObject",
        "name": "IntProperty"
      },
      "super": null,
      "template": {
        "package": "/Script/CoreUObject",
        "name": "Default__IntProperty"
      },
      "outer": {
        "package": "{{THIS PACKAGE}}",
        "name": "ExecuteUbergraph_Widget_MenuButton"
      },
      "properties": {}
    },
    {
      "name": "HorizontalBox",
      "class": {
        "package": "/Script/UMG",
        "name": "HorizontalBox"
      },
      "super": null,
      "template": {
        "package": "/Script/UMG",
        "name": "Default__HorizontalBox"
      },
      "outer": {
        "package": "{{THIS PACKAGE}}",
        "name": "{{BROKEN/MISSING EXPORT}}"
      },
      "properties": {
        "Slot": {
          "type": "ObjectProperty",
          "value": {
            "type": "reference",
            "value": {
              "package": "{{THIS PACKAGE}}",
              "name": "OverlaySlot"
            }
          }
        },
        "Slots": {
          "type": "ArrayProperty",
          "value": [
            {
              "type": "reference",
              "value": {
                "package": "{{THIS PACKAGE}}",
                "name": "HorizontalBoxSlot"
              }
            },
            {
              "type": "reference",
              "value": {
                "package": "{{THIS PACKAGE}}",
                "name": "HorizontalBoxSlot"
              }
            }
          ]
        }
      }
    },
    {
      "name": "CallFunc_GetFactoryGameOrange_OrangeText",
      "class": {
        "package": "/Script/CoreUObject",
        "name": "StructProperty"
      },
      "super": null,
      "template": {
        "package": "/Script/CoreUObject",
        "name": "Default__StructProperty"
      },
      "outer": {
        "package": "{{THIS PACKAGE}}",
        "name": "GetHoverColor"
      },
      "properties": {}
    },
    {
      "name": "CallFunc_GetFactoryGameWhite_GraphicsWhite2",
      "class": {
        "package": "/Script/CoreUObject",
        "name": "StructProperty"
      },
      "super": null,
      "template": {
        "package": "/Script/CoreUObject",
        "name": "Default__StructProperty"
      },
      "outer": {
        "package": "{{THIS PACKAGE}}",
        "name": "GetHoverColor"
      },
      "properties": {}
    },
    {
      "name": "mText",
      "class": {
        "package": "/Script/CoreUObject",
        "name": "TextProperty"
      },
      "super": null,
      "template": {
        "package": "/Script/CoreUObject",
        "name": "Default__TextProperty"
      },
      "outer": {
        "package": "{{THIS PACKAGE}}",
        "name": "Widget_MenuButton_C"
      },
      "properties": {}
    },
    {
      "name": "EntryPoint",
      "class": {
        "package": "/Script/CoreUObject",
        "name": "IntProperty"
      },
      "super": null,
      "template": {
        "package": "/Script/CoreUObject",
        "name": "Default__IntProperty"
      },
      "outer": {
        "package": "{{THIS PACKAGE}}",
        "name": "{{BROKEN/MISSING EXPORT}}"
      },
      "properties": {}
    },
    {
      "name": "ExecuteUbergraph_Widget_MenuButton",
      "class": {
        "package": "/Script/CoreUObject",
        "name": "Function"
      },
      "super": null,
      "template": {
        "package": "/Script/CoreUObject",
        "name": "Default__Function"
      },
      "outer": {
        "package": "{{THIS PACKAGE}}",
        "name": "Widget_MenuButton_C"
      },
      "properties": {}
    },
    {
      "name": "ButtonText",
      "class": {
        "package": "/Script/CoreUObject",
        "name": "ObjectProperty"
      },
      "super": null,
      "template": {
        "package": "/Script/CoreUObject",
        "name": "Default__ObjectProperty"
      },
      "outer": {
        "package": "{{THIS PACKAGE}}",
        "name": "Widget_MenuButton_C"
      },
      "properties": {}
    },
    {
      "name": "CallFunc_IsValid_ReturnValue",
      "class": {
        "package": "/Script/CoreUObject",
        "name": "BoolProperty"
      },
      "super": null,
      "template": {
        "package": "/Script/CoreUObject",
        "name": "Default__BoolProperty"
      },
      "outer": {
        "package": "{{THIS PACKAGE}}",
        "name": "GetHoverColor"
      },
      "properties": {}
    },
    {
      "name": "ButtonSlot",
      "class": {
        "package": "/Script/UMG",
        "name": "ButtonSlot"
      },
      "super": null,
      "template": {
        "package": "/Script/UMG",
        "name": "Default__ButtonSlot"
      },
      "outer": {
        "package": "{{THIS PACKAGE}}",
        "name": "MenuButton"
      },
      "properties": {
        "Content": {
          "type": "ObjectProperty",
          "value": {
            "type": "reference",
            "value": {
              "package": "{{THIS PACKAGE}}",
              "name": "Overlay"
            }
          }
        },
        "HorizontalAlignment": {
          "type": "ByteProperty",
          "value": "HAlign_Fill"
        },
        "Padding": {
          "type": "Margin",
          "value": {
            "Bottom": {
              "type": "FloatProperty",
              "value": 0
            },
            "Left": {
              "type": "FloatProperty",
              "value": 0
            },
            "Right": {
              "type": "FloatProperty",
              "value": 0
            },
            "Top": {
              "type": "FloatProperty",
              "value": 0
            }
          }
        },
        "Parent": {
          "type": "ObjectProperty",
          "value": {
            "type": "reference",
            "value": {
              "package": "{{THIS PACKAGE}}",
              "name": "MenuButton"
            }
          }
        },
        "VerticalAlignment": {
          "type": "ByteProperty",
          "value": "VAlign_Bottom"
        }
      }
    },
    {
      "name": "ButtonSlot",
      "class": {
        "package": "/Script/UMG",
        "name": "ButtonSlot"
      },
      "super": null,
      "template": {
        "package": "/Script/UMG",
        "name": "Default__ButtonSlot"
      },
      "outer": {
        "package": "{{THIS PACKAGE}}",
        "name": "MenuButton"
      },
      "properties": {
        "Content": {
          "type": "ObjectProperty",
          "value": {
            "type": "reference",
            "value": {
              "package": "{{THIS PACKAGE}}",
              "name": "Overlay"
            }
          }
        },
        "HorizontalAlignment": {
          "type": "ByteProperty",
          "value": "HAlign_Fill"
        },
        "Padding": {
          "type": "Margin",
          "value": {
            "Bottom": {
              "type": "FloatProperty",
              "value": 0
            },
            "Left": {
              "type": "FloatProperty",
              "value": 0
            },
            "Right": {
              "type": "FloatProperty",
              "value": 0
            },
            "Top": {
              "type": "FloatProperty",
              "value": 0
            }
          }
        },
        "Parent": {
          "type": "ObjectProperty",
          "value": {
            "type": "reference",
            "value": {
              "package": "{{THIS PACKAGE}}",
              "name": "MenuButton"
            }
          }
        },
        "VerticalAlignment": {
          "type": "ByteProperty",
          "value": "VAlign_Bottom"
        }
      }
    },
    {
      "name": "Overlay",
      "class": {
        "package": "/Script/UMG",
        "name": "Overlay"
      },
      "super": null,
      "template": {
        "package": "/Script/UMG",
        "name": "Default__Overlay"
      },
      "outer": {
        "package": "{{THIS PACKAGE}}",
        "name": "{{BROKEN/MISSING EXPORT}}"
      },
      "properties": {
        "Slot": {
          "type": "ObjectProperty",
          "value": {
            "type": "reference",
            "value": {
              "package": "{{THIS PACKAGE}}",
              "name": "HorizontalBoxSlot"
            }
          }
        },
        "Slots": {
          "type": "ArrayProperty",
          "value": [
            {
              "type": "reference",
              "value": {
                "package": "{{THIS PACKAGE}}",
                "name": "OverlaySlot"
              }
            },
            {
              "type": "reference",
              "value": {
                "package": "{{THIS PACKAGE}}",
                "name": "OverlaySlot"
              }
            }
          ]
        }
      }
    },
    {
      "name": "SetFocused",
      "class": {
        "package": "/Script/CoreUObject",
        "name": "Function"
      },
      "super": null,
      "template": {
        "package": "/Script/CoreUObject",
        "name": "Default__Function"
      },
      "outer": {
        "package": "{{THIS PACKAGE}}",
        "name": "Widget_MenuButton_C"
      },
      "properties": {}
    },
    {
      "name": "ButtonImage",
      "class": {
        "package": "/Script/UMG",
        "name": "Image"
      },
      "super": null,
      "template": {
        "package": "/Script/UMG",
        "name": "Default__Image"
      },
      "outer": {
        "package": "{{THIS PACKAGE}}",
        "name": "{{BROKEN/MISSING EXPORT}}"
      },
      "properties": {
        "Brush": {
          "type": "SlateBrush",
          "value": {
            "DrawAs": {
              "type": "ByteProperty",
              "value": "ESlateBrushDrawType::Box"
            },
            "Margin": {
              "type": "Margin",
              "value": {
                "Bottom": {
                  "type": "FloatProperty",
                  "value": 0.38
                },
                "Left": {
                  "type": "FloatProperty",
                  "value": 0.38
                },
                "Right": {
                  "type": "FloatProperty",
                  "value": 0.38
                },
                "Top": {
                  "type": "FloatProperty",
                  "value": 0.38
                }
              }
            },
            "ResourceObject": {
              "type": "ObjectProperty",
              "value": {
                "type": "reference",
                "value": {
                  "package": "/Game/FactoryGame/Interface/UI/Assets/Shared/WindowWidget/RectangleBackground_Rounded",
                  "name": "RectangleBackground_Rounded"
                }
              }
            }
          }
        },
        "Slot": {
          "type": "ObjectProperty",
          "value": {
            "type": "reference",
            "value": {
              "package": "{{THIS PACKAGE}}",
              "name": "OverlaySlot"
            }
          }
        },
        "bIsVariable": {
          "type": "BoolProperty",
          "value": false
        }
      }
    },
    {
      "name": "OverlaySlot",
      "class": {
        "package": "/Script/UMG",
        "name": "OverlaySlot"
      },
      "super": null,
      "template": {
        "package": "/Script/UMG",
        "name": "Default__OverlaySlot"
      },
      "outer": {
        "package": "{{THIS PACKAGE}}",
        "name": "Overlay"
      },
      "properties": {
        "Content": {
          "type": "ObjectProperty",
          "value": {
            "type": "reference",
            "value": {
              "package": "{{THIS PACKAGE}}",
              "name": "buttonSize"
            }
          }
        },
        "HorizontalAlignment": {
          "type": "ByteProperty",
          "value": "HAlign_Fill"
        },
        "Parent": {
          "type": "ObjectProperty",
          "value": {
            "type": "reference",
            "value": {
              "package": "{{THIS PACKAGE}}",
              "name": "Overlay"
            }
          }
        },
        "VerticalAlignment": {
          "type": "ByteProperty",
          "value": "VAlign_Fill"
        }
      }
    },
    {
      "name": "CallFunc_BooleanAND_ReturnValue",
      "class": {
        "package": "/Script/CoreUObject",
        "name": "BoolProperty"
      },
      "super": null,
      "template": {
        "package": "/Script/CoreUObject",
        "name": "Default__BoolProperty"
      },
      "outer": {
        "package": "{{THIS PACKAGE}}",
        "name": "ExecuteUbergraph_Widget_MenuButton"
      },
      "properties": {}
    },
    {
      "name": "HideButton",
      "class": {
        "package": "/Script/CoreUObject",
        "name": "Function"
      },
      "super": null,
      "template": {
        "package": "/Script/CoreUObject",
        "name": "Default__Function"
      },
      "outer": {
        "package": "{{THIS PACKAGE}}",
        "name": "Widget_MenuButton_C"
      },
      "properties": {}
    },
    {
      "name": "ButtonText",
      "class": {
        "package": "/Script/UMG",
        "name": "TextBlock"
      },
      "super": null,
      "template": {
        "package": "/Script/UMG",
        "name": "Default__TextBlock"
      },
      "outer": {
        "package": "{{THIS PACKAGE}}",
        "name": "{{BROKEN/MISSING EXPORT}}"
      },
      "properties": {
        "ColorAndOpacity": {
          "type": "SlateColor",
          "value": {
            "SpecifiedColor": {
              "type": "LinearColor",
              "value": {
                "r": 0.132868,
                "g": 0.132868,
                "b": 0.135633,
                "a": 1
              }
            }
          }
        },
        "Font": {
          "type": "SlateFontInfo",
          "value": {
            "FontObject": {
              "type": "ObjectProperty",
              "value": {
                "type": "reference",
                "value": {
                  "package": "/Game/FactoryGame/Interface/Font/DescriptionText",
                  "name": "DescriptionText"
                }
              }
            },
            "Size": {
              "type": "IntProperty",
              "value": 14
            },
            "TypefaceFontName": {
              "type": "NameProperty",
              "value": "Default"
            }
          }
        },
        "Slot": {
          "type": "ObjectProperty",
          "value": {
            "type": "reference",
            "value": {
              "package": "{{THIS PACKAGE}}",
              "name": "HorizontalBoxSlot"
            }
          }
        },
        "Text": {
          "type": "TextProperty",
          "value": {
            "flags": 0,
            "history_type": 0,
            "namespace": "",
            "key": "54A49EFF4CAA78C592A256A2E2E5DE71",
            "source_string": "Text Block"
          }
        }
      }
    },
    {
      "name": "Temp_int_Loop_Counter_Variable",
      "class": {
        "package": "/Script/CoreUObject",
        "name": "IntProperty"
      },
      "super": null,
      "template": {
        "package": "/Script/CoreUObject",
        "name": "Default__IntProperty"
      },
      "outer": {
        "package": "{{THIS PACKAGE}}",
        "name": "ExecuteUbergraph_Widget_MenuButton"
      },
      "properties": {}
    },
    {
      "name": "buttonSize",
      "class": {
        "package": "/Script/UMG",
        "name": "Spacer"
      },
      "super": null,
      "template": {
        "package": "/Script/UMG",
        "name": "Default__Spacer"
      },
      "outer": {
        "package": "{{THIS PACKAGE}}",
        "name": "{{BROKEN/MISSING EXPORT}}"
      },
      "properties": {
        "Size": {
          "type": "Vector2D",
          "value": {
            "x": 360,
            "y": 1
          }
        },
        "Slot": {
          "type": "ObjectProperty",
          "value": {
            "type": "reference",
            "value": {
              "package": "{{THIS PACKAGE}}",
              "name": "OverlaySlot"
            }
          }
        },
        "Visibility": {
          "type": "ESlateVisibility",
          "value": "ESlateVisibility::HitTestInvisible"
        }
      }
    },
    {
      "name": "CallFunc_GetFactoryGameDarkGray_Graphics",
      "class": {
        "package": "/Script/CoreUObject",
        "name": "StructProperty"
      },
      "super": null,
      "template": {
        "package": "/Script/CoreUObject",
        "name": "Default__StructProperty"
      },
      "outer": {
        "package": "{{THIS PACKAGE}}",
        "name": "GetButtonColor"
      },
      "properties": {}
    },
    {
      "name": "SizeBox",
      "class": {
        "package": "/Script/UMG",
        "name": "SizeBox"
      },
      "super": null,
      "template": {
        "package": "/Script/UMG",
        "name": "Default__SizeBox"
      },
      "outer": {
        "package": "{{THIS PACKAGE}}",
        "name": "{{BROKEN/MISSING EXPORT}}"
      },
      "properties": {
        "HeightOverride": {
          "type": "FloatProperty",
          "value": 26
        },
        "Slot": {
          "type": "ObjectProperty",
          "value": {
            "type": "reference",
            "value": {
              "package": "{{THIS PACKAGE}}",
              "name": "OverlaySlot"
            }
          }
        },
        "Slots": {
          "type": "ArrayProperty",
          "value": [
            {
              "type": "reference",
              "value": {
                "package": "{{THIS PACKAGE}}",
                "name": "SizeBoxSlot"
              }
            }
          ]
        },
        "WidthOverride": {
          "type": "FloatProperty",
          "value": 26
        },
        "bOverride_HeightOverride": {
          "type": "BoolProperty",
          "value": true
        },
        "bOverride_WidthOverride": {
          "type": "BoolProperty",
          "value": true
        }
      }
    },
    {
      "name": "CallFunc_IsHovered_ReturnValue",
      "class": {
        "package": "/Script/CoreUObject",
        "name": "BoolProperty"
      },
      "super": null,
      "template": {
        "package": "/Script/CoreUObject",
        "name": "Default__BoolProperty"
      },
      "outer": {
        "package": "{{THIS PACKAGE}}",
        "name": "GetButtonColor"
      },
      "properties": {}
    },
    {
      "name": "ButtonImage",
      "class": {
        "package": "/Script/UMG",
        "name": "Image"
      },
      "super": null,
      "template": {
        "package": "/Script/UMG",
        "name": "Default__Image"
      },
      "outer": {
        "package": "{{THIS PACKAGE}}",
        "name": "{{BROKEN/MISSING EXPORT}}"
      },
      "properties": {
        "Brush": {
          "type": "SlateBrush",
          "value": {
            "DrawAs": {
              "type": "ByteProperty",
              "value": "ESlateBrushDrawType::Box"
            },
            "Margin": {
              "type": "Margin",
              "value": {
                "Bottom": {
                  "type": "FloatProperty",
                  "value": 0.38
                },
                "Left": {
                  "type": "FloatProperty",
                  "value": 0.38
                },
                "Right": {
                  "type": "FloatProperty",
                  "value": 0.38
                },
                "Top": {
                  "type": "FloatProperty",
                  "value": 0.38
                }
              }
            },
            "ResourceObject": {
              "type": "ObjectProperty",
              "value": {
                "type": "reference",
                "value": {
                  "package": "/Game/FactoryGame/Interface/UI/Assets/Shared/WindowWidget/RectangleBackground_Rounded",
                  "name": "RectangleBackground_Rounded"
                }
              }
            }
          }
        },
        "Slot": {
          "type": "ObjectProperty",
          "value": {
            "type": "reference",
            "value": {
              "package": "{{THIS PACKAGE}}",
              "name": "OverlaySlot"
            }
          }
        },
        "bIsVariable": {
          "type": "BoolProperty",
          "value": false
        }
      }
    },
    {
      "name": "Widget_MenuButton_C",
      "class": {
        "package": "/Script/UMG",
        "name": "WidgetBlueprintGeneratedClass"
      },
      "super": {
        "package": "/Script/FactoryGame",
        "name": "FGButtonWidget"
      },
      "template": {
        "package": "/Script/UMG",
        "name": "Default__WidgetBlueprintGeneratedClass"
      },
      "outer": null,
      "properties": {
        "Bindings": {
          "type": "ArrayProperty",
          "value": [
            {
              "type": "DelegateRuntimeBinding",
              "value": {
                "FunctionName": {
                  "type": "NameProperty",
                  "value": "None"
                },
                "Kind": {
                  "type": "EBindingKind",
                  "value": "EBindingKind::Property"
                },
                "ObjectName": {
                  "type": "StrProperty",
                  "value": "ButtonText"
                },
                "PropertyName": {
                  "type": "NameProperty",
                  "value": "Text"
                },
                "SourcePath": {
                  "type": "DynamicPropertyPath",
                  "value": {
                    "CachedFunction": {
                      "type": "ObjectProperty",
                      "value": {
                        "type": "reference",
                        "value": null
                      }
                    },
                    "Segments": {
                      "type": "ArrayProperty",
                      "value": [
                        {
                          "type": "PropertyPathSegment",
                          "value": {
                            "ArrayIndex": {
                              "type": "IntProperty",
                              "value": -1
                            },
                            "Name": {
                              "type": "NameProperty",
                              "value": "mText"
                            }
                          }
                        }
                      ]
                    }
                  }
                }
              }
            },
            {
              "type": "DelegateRuntimeBinding",
              "value": {
                "FunctionName": {
                  "type": "NameProperty",
                  "value": "None"
                },
                "Kind": {
                  "type": "EBindingKind",
                  "value": "EBindingKind::Property"
                },
                "ObjectName": {
                  "type": "StrProperty",
                  "value": "mOptionsIcon"
                },
                "PropertyName": {
                  "type": "NameProperty",
                  "value": "Brush"
                },
                "SourcePath": {
                  "type": "DynamicPropertyPath",
                  "value": {
                    "CachedFunction": {
                      "type": "ObjectProperty",
                      "value": {
                        "type": "reference",
                        "value": null
                      }
                    },
                    "Segments": {
                      "type": "ArrayProperty",
                      "value": [
                        {
                          "type": "PropertyPathSegment",
                          "value": {
                            "ArrayIndex": {
                              "type": "IntProperty",
                              "value": -1
                            },
                            "Name": {
                              "type": "NameProperty",
                              "value": "mBrush"
                            }
                          }
                        }
                      ]
                    }
                  }
                }
              }
            },
            {
              "type": "DelegateRuntimeBinding",
              "value": {
                "FunctionName": {
                  "type": "NameProperty",
                  "value": "Get_ButtonImage_ColorAndOpacity"
                },
                "Kind": {
                  "type": "EBindingKind",
                  "value": "EBindingKind::Function"
                },
                "ObjectName": {
                  "type": "StrProperty",
                  "value": "ButtonImage"
                },
                "PropertyName": {
                  "type": "NameProperty",
                  "value": "ColorAndOpacity"
                },
                "SourcePath": {
                  "type": "DynamicPropertyPath",
                  "value": {
                    "CachedFunction": {
                      "type": "ObjectProperty",
                      "value": {
                        "type": "reference",
                        "value": null
                      }
                    },
                    "Segments": {
                      "type": "ArrayProperty",
                      "value": [
                        {
                          "type": "PropertyPathSegment",
                          "value": {
                            "ArrayIndex": {
                              "type": "IntProperty",
                              "value": -1
                            },
                            "Name": {
                              "type": "NameProperty",
                              "value": "GetHoverColor"
                            }
                          }
                        }
                      ]
                    }
                  }
                }
              }
            }
          ]
        },
        "DynamicBindingObjects": {
          "type": "ArrayProperty",
          "value": [
            {
              "type": "reference",
              "value": {
                "package": "{{THIS PACKAGE}}",
                "name": "ComponentDelegateBinding"
              }
            }
          ]
        },
        "TemplateAsset": {
          "type": "SoftObjectProperty",
          "value": {
            "asset_path_name": "/Game/FactoryGame/Interface/UI/Menu/Widget_MenuButton.WidgetArchetype",
            "sub_path": ""
          }
        },
        "UberGraphFramePointerProperty": {
          "type": "ObjectProperty",
          "value": {
            "type": "reference",
            "value": {
              "package": "{{THIS PACKAGE}}",
              "name": "UberGraphFrame"
            }
          }
        },
        "UberGraphFunction": {
          "type": "ObjectProperty",
          "value": {
            "type": "reference",
            "value": {
              "package": "{{THIS PACKAGE}}",
              "name": "ExecuteUbergraph_Widget_MenuButton"
            }
          }
        },
        "WidgetTree": {
          "type": "ObjectProperty",
          "value": {
            "type": "reference",
            "value": {
              "package": "{{THIS PACKAGE}}",
              "name": "WidgetTree"
            }
          }
        },
        "bAllowTemplate": {
          "type": "BoolProperty",
          "value": true
        },
        "bClassRequiresNativeTick": {
          "type": "BoolProperty",
          "value": true
        },
        "bValidTemplate": {
          "type": "BoolProperty",
          "value": true
        }
      }
    },
    {
      "name": "CallFunc_SelectColor_ReturnValue",
      "class": {
        "package": "/Script/CoreUObject",
        "name": "StructProperty"
      },
      "super": null,
      "template": {
        "package": "/Script/CoreUObject",
        "name": "Default__StructProperty"
      },
      "outer": {
        "package": "{{THIS PACKAGE}}",
        "name": "GetHoverColor"
      },
      "properties": {}
    },
    {
      "name": "CallFunc_EqualEqual_IntInt_ReturnValue",
      "class": {
        "package": "/Script/CoreUObject",
        "name": "BoolProperty"
      },
      "super": null,
      "template": {
        "package": "/Script/CoreUObject",
        "name": "Default__BoolProperty"
      },
      "outer": {
        "package": "{{THIS PACKAGE}}",
        "name": "GetButtonColor"
      },
      "properties": {}
    },
    {
      "name": "SizeBoxSlot",
      "class": {
        "package": "/Script/UMG",
        "name": "SizeBoxSlot"
      },
      "super": null,
      "template": {
        "package": "/Script/UMG",
        "name": "Default__SizeBoxSlot"
      },
      "outer": {
        "package": "{{THIS PACKAGE}}",
        "name": "SizeBox"
      },
      "properties": {
        "Content": {
          "type": "ObjectProperty",
          "value": {
            "type": "reference",
            "value": {
              "package": "{{THIS PACKAGE}}",
              "name": "mOptionsIcon"
            }
          }
        },
        "Parent": {
          "type": "ObjectProperty",
          "value": {
            "type": "reference",
            "value": {
              "package": "{{THIS PACKAGE}}",
              "name": "SizeBox"
            }
          }
        }
      }
    },
    {
      "name": "CallFunc_GetChildIndex_ReturnValue",
      "class": {
        "package": "/Script/CoreUObject",
        "name": "IntProperty"
      },
      "super": null,
      "template": {
        "package": "/Script/CoreUObject",
        "name": "Default__IntProperty"
      },
      "outer": {
        "package": "{{THIS PACKAGE}}",
        "name": "ExecuteUbergraph_Widget_MenuButton"
      },
      "properties": {}
    },
    {
      "name": "CallFunc_GetFactoryGameWhite_GraphicsWhite1",
      "class": {
        "package": "/Script/CoreUObject",
        "name": "StructProperty"
      },
      "super": null,
      "template": {
        "package": "/Script/CoreUObject",
        "name": "Default__StructProperty"
      },
      "outer": {
        "package": "{{THIS PACKAGE}}",
        "name": "GetButtonColor"
      },
      "properties": {}
    },
    {
      "name": "CallFunc_GetFactoryGameWhite_TextWhite1",
      "class": {
        "package": "/Script/CoreUObject",
        "name": "StructProperty"
      },
      "super": null,
      "template": {
        "package": "/Script/CoreUObject",
        "name": "Default__StructProperty"
      },
      "outer": {
        "package": "{{THIS PACKAGE}}",
        "name": "GetHoverColor"
      },
      "properties": {}
    },
    {
      "name": "InFocusEvent",
      "class": {
        "package": "/Script/CoreUObject",
        "name": "StructProperty"
      },
      "super": null,
      "template": {
        "package": "/Script/CoreUObject",
        "name": "Default__StructProperty"
      },
      "outer": {
        "package": "{{THIS PACKAGE}}",
        "name": "OnFocusReceived"
      },
      "properties": {}
    },
    {
      "name": "WidgetTree",
      "class": {
        "package": "/Script/UMG",
        "name": "WidgetTree"
      },
      "super": null,
      "template": {
        "package": "/Script/UMG",
        "name": "Default__WidgetTree"
      },
      "outer": {
        "package": "{{THIS PACKAGE}}",
        "name": "Widget_MenuButton_C"
      },
      "properties": {
        "RootWidget": {
          "type": "ObjectProperty",
          "value": {
            "type": "reference",
            "value": {
              "package": "{{THIS PACKAGE}}",
              "name": "MenuButton"
            }
          }
        }
      }
    },
    {
      "name": "OnFocusReceived",
      "class": {
        "package": "/Script/CoreUObject",
        "name": "Function"
      },
      "super": {
        "package": "UserWidget",
        "name": "OnFocusReceived"
      },
      "template": {
        "package": "/Script/CoreUObject",
        "name": "Default__Function"
      },
      "outer": {
        "package": "{{THIS PACKAGE}}",
        "name": "Widget_MenuButton_C"
      },
      "properties": {}
    },
    {
      "name": "CallFunc_EqualEqual_IntInt_ReturnValue",
      "class": {
        "package": "/Script/CoreUObject",
        "name": "BoolProperty"
      },
      "super": null,
      "template": {
        "package": "/Script/CoreUObject",
        "name": "Default__BoolProperty"
      },
      "outer": {
        "package": "{{THIS PACKAGE}}",
        "name": "GetHoverColor"
      },
      "properties": {}
    },
    {
      "name": "CallFunc_GetFactoryGameWhite_GraphicsWhite1",
      "class": {
        "package": "/Script/CoreUObject",
        "name": "StructProperty"
      },
      "super": null,
      "template": {
        "package": "/Script/CoreUObject",
        "name": "Default__StructProperty"
      },
      "outer": {
        "package": "{{THIS PACKAGE}}",
        "name": "GetHoverColor"
      },
      "properties": {}
    },
    {
      "name": "mCachedTabSwitcher",
      "class": {
        "package": "/Script/CoreUObject",
        "name": "ObjectProperty"
      },
      "super": null,
      "template": {
        "package": "/Script/CoreUObject",
        "name": "Default__ObjectProperty"
      },
      "outer": {
        "package": "{{THIS PACKAGE}}",
        "name": "Widget_MenuButton_C"
      },
      "properties": {}
    },
    {
      "name": "OverlaySlot",
      "class": {
        "package": "/Script/UMG",
        "name": "OverlaySlot"
      },
      "super": null,
      "template": {
        "package": "/Script/UMG",
        "name": "Default__OverlaySlot"
      },
      "outer": {
        "package": "{{THIS PACKAGE}}",
        "name": "Overlay"
      },
      "properties": {
        "Content": {
          "type": "ObjectProperty",
          "value": {
            "type": "reference",
            "value": {
              "package": "{{THIS PACKAGE}}",
              "name": "ButtonImage"
            }
          }
        },
        "HorizontalAlignment": {
          "type": "ByteProperty",
          "value": "HAlign_Fill"
        },
        "Parent": {
          "type": "ObjectProperty",
          "value": {
            "type": "reference",
            "value": {
              "package": "{{THIS PACKAGE}}",
              "name": "Overlay"
            }
          }
        },
        "VerticalAlignment": {
          "type": "ByteProperty",
          "value": "VAlign_Fill"
        }
      }
    },
    {
      "name": "OverlaySlot",
      "class": {
        "package": "/Script/UMG",
        "name": "OverlaySlot"
      },
      "super": null,
      "template": {
        "package": "/Script/UMG",
        "name": "Default__OverlaySlot"
      },
      "outer": {
        "package": "{{THIS PACKAGE}}",
        "name": "Overlay"
      },
      "properties": {
        "Content": {
          "type": "ObjectProperty",
          "value": {
            "type": "reference",
            "value": {
              "package": "{{THIS PACKAGE}}",
              "name": "ButtonImage"
            }
          }
        },
        "HorizontalAlignment": {
          "type": "ByteProperty",
          "value": "HAlign_Fill"
        },
        "Parent": {
          "type": "ObjectProperty",
          "value": {
            "type": "reference",
            "value": {
              "package": "{{THIS PACKAGE}}",
              "name": "Overlay"
            }
          }
        },
        "VerticalAlignment": {
          "type": "ByteProperty",
          "value": "VAlign_Fill"
        }
      }
    },
    {
      "name": "buttonSize",
      "class": {
        "package": "/Script/UMG",
        "name": "Spacer"
      },
      "super": null,
      "template": {
        "package": "/Script/UMG",
        "name": "Default__Spacer"
      },
      "outer": {
        "package": "{{THIS PACKAGE}}",
        "name": "{{BROKEN/MISSING EXPORT}}"
      },
      "properties": {
        "Size": {
          "type": "Vector2D",
          "value": {
            "x": 360,
            "y": 1
          }
        },
        "Slot": {
          "type": "ObjectProperty",
          "value": {
            "type": "reference",
            "value": {
              "package": "{{THIS PACKAGE}}",
              "name": "OverlaySlot"
            }
          }
        },
        "Visibility": {
          "type": "ESlateVisibility",
          "value": "ESlateVisibility::HitTestInvisible"
        }
      }
    },
    {
      "name": "OptionsIconBG",
      "class": {
        "package": "/Script/UMG",
        "name": "Image"
      },
      "super": null,
      "template": {
        "package": "/Script/UMG",
        "name": "Default__Image"
      },
      "outer": {
        "package": "{{THIS PACKAGE}}",
        "name": "{{BROKEN/MISSING EXPORT}}"
      },
      "properties": {
        "Brush": {
          "type": "SlateBrush",
          "value": {
            "ImageSize": {
              "type": "Vector2D",
              "value": {
                "x": 40,
                "y": 40
              }
            },
            "ResourceObject": {
              "type": "ObjectProperty",
              "value": {
                "type": "reference",
                "value": {
                  "package": "/Game/FactoryGame/Interface/UI/Assets/Shared/Circle_Background",
                  "name": "Circle_Background"
                }
              }
            }
          }
        },
        "ColorAndOpacity": {
          "type": "LinearColor",
          "value": {
            "r": 0.132868,
            "g": 0.132868,
            "b": 0.135633,
            "a": 1
          }
        },
        "Slot": {
          "type": "ObjectProperty",
          "value": {
            "type": "reference",
            "value": {
              "package": "{{THIS PACKAGE}}",
              "name": "OverlaySlot"
            }
          }
        },
        "bIsVariable": {
          "type": "BoolProperty",
          "value": false
        }
      }
    },
    {
      "name": "OptionsIconBG",
      "class": {
        "package": "/Script/UMG",
        "name": "Image"
      },
      "super": null,
      "template": {
        "package": "/Script/UMG",
        "name": "Default__Image"
      },
      "outer": {
        "package": "{{THIS PACKAGE}}",
        "name": "{{BROKEN/MISSING EXPORT}}"
      },
      "properties": {
        "Brush": {
          "type": "SlateBrush",
          "value": {
            "ImageSize": {
              "type": "Vector2D",
              "value": {
                "x": 40,
                "y": 40
              }
            },
            "ResourceObject": {
              "type": "ObjectProperty",
              "value": {
                "type": "reference",
                "value": {
                  "package": "/Game/FactoryGame/Interface/UI/Assets/Shared/Circle_Background",
                  "name": "Circle_Background"
                }
              }
            }
          }
        },
        "ColorAndOpacity": {
          "type": "LinearColor",
          "value": {
            "r": 0.132868,
            "g": 0.132868,
            "b": 0.135633,
            "a": 1
          }
        },
        "Slot": {
          "type": "ObjectProperty",
          "value": {
            "type": "reference",
            "value": {
              "package": "{{THIS PACKAGE}}",
              "name": "OverlaySlot"
            }
          }
        },
        "bIsVariable": {
          "type": "BoolProperty",
          "value": false
        }
      }
    },
    {
      "name": "ReturnValue",
      "class": {
        "package": "/Script/CoreUObject",
        "name": "StructProperty"
      },
      "super": null,
      "template": {
        "package": "/Script/CoreUObject",
        "name": "Default__StructProperty"
      },
      "outer": {
        "package": "{{THIS PACKAGE}}",
        "name": "OnFocusReceived"
      },
      "properties": {}
    },
    {
      "name": "OnClicked",
      "class": {
        "package": "/Script/CoreUObject",
        "name": "MulticastDelegateProperty"
      },
      "super": null,
      "template": {
        "package": "/Script/CoreUObject",
        "name": "Default__MulticastDelegateProperty"
      },
      "outer": {
        "package": "{{THIS PACKAGE}}",
        "name": "Widget_MenuButton_C"
      },
      "properties": {}
    },
    {
      "name": "CallFunc_SelectColor_ReturnValue",
      "class": {
        "package": "/Script/CoreUObject",
        "name": "StructProperty"
      },
      "super": null,
      "template": {
        "package": "/Script/CoreUObject",
        "name": "Default__StructProperty"
      },
      "outer": {
        "package": "{{THIS PACKAGE}}",
        "name": "GetButtonColor"
      },
      "properties": {}
    },
    {
      "name": "mIndexAsChild",
      "class": {
        "package": "/Script/CoreUObject",
        "name": "IntProperty"
      },
      "super": null,
      "template": {
        "package": "/Script/CoreUObject",
        "name": "Default__IntProperty"
      },
      "outer": {
        "package": "{{THIS PACKAGE}}",
        "name": "Widget_MenuButton_C"
      },
      "properties": {}
    },
    {
      "name": "SizeBoxSlot",
      "class": {
        "package": "/Script/UMG",
        "name": "SizeBoxSlot"
      },
      "super": null,
      "template": {
        "package": "/Script/UMG",
        "name": "Default__SizeBoxSlot"
      },
      "outer": {
        "package": "{{THIS PACKAGE}}",
        "name": "SizeBox"
      },
      "properties": {
        "Content": {
          "type": "ObjectProperty",
          "value": {
            "type": "reference",
            "value": {
              "package": "{{THIS PACKAGE}}",
              "name": "mOptionsIcon"
            }
          }
        },
        "Parent": {
          "type": "ObjectProperty",
          "value": {
            "type": "reference",
            "value": {
              "package": "{{THIS PACKAGE}}",
              "name": "SizeBox"
            }
          }
        }
      }
    },
    {
      "name": "CallFunc_SelectColor_ReturnValue1",
      "class": {
        "package": "/Script/CoreUObject",
        "name": "StructProperty"
      },
      "super": null,
      "template": {
        "package": "/Script/CoreUObject",
        "name": "Default__StructProperty"
      },
      "outer": {
        "package": "{{THIS PACKAGE}}",
        "name": "GetButtonColor"
      },
      "properties": {}
    },
    {
      "name": "CallFunc_GetFactoryGameWhite_GraphicsWhite",
      "class": {
        "package": "/Script/CoreUObject",
        "name": "StructProperty"
      },
      "super": null,
      "template": {
        "package": "/Script/CoreUObject",
        "name": "Default__StructProperty"
      },
      "outer": {
        "package": "{{THIS PACKAGE}}",
        "name": "GetHoverColor"
      },
      "properties": {}
    },
    {
      "name": "CallFunc_GetFactoryGameWhite_TextWhite2",
      "class": {
        "package": "/Script/CoreUObject",
        "name": "StructProperty"
      },
      "super": null,
      "template": {
        "package": "/Script/CoreUObject",
        "name": "Default__StructProperty"
      },
      "outer": {
        "package": "{{THIS PACKAGE}}",
        "name": "GetHoverColor"
      },
      "properties": {}
    },
    {
      "name": "WidgetArchetype",
      "class": {
        "package": "{{THIS PACKAGE}}",
        "name": "Widget_MenuButton_C"
      },
      "super": null,
      "template": {
        "package": "{{THIS PACKAGE}}",
        "name": "Default__Widget_MenuButton_C"
      },
      "outer": null,
      "properties": {
        "ButtonImage": {
          "type": "ObjectProperty",
          "value": {
            "type": "reference",
            "value": {
              "package": "{{THIS PACKAGE}}",
              "name": "ButtonImage"
            }
          }
        },
        "ButtonText": {
          "type": "ObjectProperty",
          "value": {
            "type": "reference",
            "value": {
              "package": "{{THIS PACKAGE}}",
              "name": "ButtonText"
            }
          }
        },
        "MenuButton": {
          "type": "ObjectProperty",
          "value": {
            "type": "reference",
            "value": {
              "package": "{{THIS PACKAGE}}",
              "name": "MenuButton"
            }
          }
        },
        "WidgetTree": {
          "type": "ObjectProperty",
          "value": {
            "type": "reference",
            "value": {
              "package": "{{THIS PACKAGE}}",
              "name": "WidgetTree"
            }
          }
        },
        "bCookedWidgetTree": {
          "type": "BoolProperty",
          "value": true
        },
        "mOptionsIcon": {
          "type": "ObjectProperty",
          "value": {
            "type": "reference",
            "value": {
              "package": "{{THIS PACKAGE}}",
              "name": "mOptionsIcon"
            }
          }
        }
      }
    },
    {
      "name": "MenuButton",
      "class": {
        "package": "/Script/UMG",
        "name": "Button"
      },
      "super": null,
      "template": {
        "package": "/Script/UMG",
        "name": "Default__Button"
      },
      "outer": {
        "package": "{{THIS PACKAGE}}",
        "name": "{{BROKEN/MISSING EXPORT}}"
      },
      "properties": {
        "Slots": {
          "type": "ArrayProperty",
          "value": [
            {
              "type": "reference",
              "value": {
                "package": "{{THIS PACKAGE}}",
                "name": "ButtonSlot"
              }
            }
          ]
        },
        "WidgetStyle": {
          "type": "ButtonStyle",
          "value": {
            "Hovered": {
              "type": "SlateBrush",
              "value": {
                "DrawAs": {
                  "type": "ByteProperty",
                  "value": "ESlateBrushDrawType::NoDrawType"
                }
              }
            },
            "Normal": {
              "type": "SlateBrush",
              "value": {
                "DrawAs": {
                  "type": "ByteProperty",
                  "value": "ESlateBrushDrawType::NoDrawType"
                }
              }
            },
            "Pressed": {
              "type": "SlateBrush",
              "value": {
                "DrawAs": {
                  "type": "ByteProperty",
                  "value": "ESlateBrushDrawType::NoDrawType"
                }
              }
            },
            "PressedPadding": {
              "type": "Margin",
              "value": {
                "Bottom": {
                  "type": "FloatProperty",
                  "value": 2
                },
                "Top": {
                  "type": "FloatProperty",
                  "value": 2
                }
              }
            }
          }
        }
      }
    },
    {
      "name": "Temp_int_Array_Index_Variable",
      "class": {
        "package": "/Script/CoreUObject",
        "name": "IntProperty"
      },
      "super": null,
      "template": {
        "package": "/Script/CoreUObject",
        "name": "Default__IntProperty"
      },
      "outer": {
        "package": "{{THIS PACKAGE}}",
        "name": "ExecuteUbergraph_Widget_MenuButton"
      },
      "properties": {}
    },
    {
      "name": "WidgetTree",
      "class": {
        "package": "/Script/UMG",
        "name": "WidgetTree"
      },
      "super": null,
      "template": {
        "package": "/Script/UMG",
        "name": "Default__WidgetTree"
      },
      "outer": {
        "package": "{{THIS PACKAGE}}",
        "name": "WidgetArchetype"
      },
      "properties": {
        "RootWidget": {
          "type": "ObjectProperty",
          "value": {
            "type": "reference",
            "value": {
              "package": "{{THIS PACKAGE}}",
              "name": "MenuButton"
            }
          }
        }
      }
    },
    {
      "name": "Construct",
      "class": {
        "package": "/Script/CoreUObject",
        "name": "Function"
      },
      "super": {
        "package": "UserWidget",
        "name": "Construct"
      },
      "template": {
        "package": "/Script/CoreUObject",
        "name": "Default__Function"
      },
      "outer": {
        "package": "{{THIS PACKAGE}}",
        "name": "Widget_MenuButton_C"
      },
      "properties": {}
    },
    {
      "name": "CallFunc_IsValid_ReturnValue",
      "class": {
        "package": "/Script/CoreUObject",
        "name": "BoolProperty"
      },
      "super": null,
      "template": {
        "package": "/Script/CoreUObject",
        "name": "Default__BoolProperty"
      },
      "outer": {
        "package": "{{THIS PACKAGE}}",
        "name": "GetButtonColor"
      },
      "properties": {}
    },
    {
      "name": "MenuButton",
      "class": {
        "package": "/Script/CoreUObject",
        "name": "ObjectProperty"
      },
      "super": null,
      "template": {
        "package": "/Script/CoreUObject",
        "name": "Default__ObjectProperty"
      },
      "outer": {
        "package": "{{THIS PACKAGE}}",
        "name": "Widget_MenuButton_C"
      },
      "properties": {}
    },
    {
      "name": "Temp_bool_True_if_break_was_hit_Variable",
      "class": {
        "package": "/Script/CoreUObject",
        "name": "BoolProperty"
      },
      "super": null,
      "template": {
        "package": "/Script/CoreUObject",
        "name": "Default__BoolProperty"
      },
      "outer": {
        "package": "{{THIS PACKAGE}}",
        "name": "ExecuteUbergraph_Widget_MenuButton"
      },
      "properties": {}
    },
    {
      "name": "OnThisMenuButtonClicked",
      "class": {
        "package": "/Script/CoreUObject",
        "name": "Function"
      },
      "super": null,
      "template": {
        "package": "/Script/CoreUObject",
        "name": "Default__Function"
      },
      "outer": {
        "package": "{{THIS PACKAGE}}",
        "name": "Widget_MenuButton_C"
      },
      "properties": {}
    },
    {
      "name": "OverlaySlot",
      "class": {
        "package": "/Script/UMG",
        "name": "OverlaySlot"
      },
      "super": null,
      "template": {
        "package": "/Script/UMG",
        "name": "Default__OverlaySlot"
      },
      "outer": {
        "package": "{{THIS PACKAGE}}",
        "name": "Overlay"
      },
      "properties": {
        "Content": {
          "type": "ObjectProperty",
          "value": {
            "type": "reference",
            "value": {
              "package": "{{THIS PACKAGE}}",
              "name": "OptionsIconBG"
            }
          }
        },
        "Parent": {
          "type": "ObjectProperty",
          "value": {
            "type": "reference",
            "value": {
              "package": "{{THIS PACKAGE}}",
              "name": "Overlay"
            }
          }
        }
      }
    },
    {
      "name": "ButtonImage",
      "class": {
        "package": "/Script/CoreUObject",
        "name": "ObjectProperty"
      },
      "super": null,
      "template": {
        "package": "/Script/CoreUObject",
        "name": "Default__ObjectProperty"
      },
      "outer": {
        "package": "{{THIS PACKAGE}}",
        "name": "Widget_MenuButton_C"
      },
      "properties": {}
    },
    {
      "name": "OverlaySlot",
      "class": {
        "package": "/Script/UMG",
        "name": "OverlaySlot"
      },
      "super": null,
      "template": {
        "package": "/Script/UMG",
        "name": "Default__OverlaySlot"
      },
      "outer": {
        "package": "{{THIS PACKAGE}}",
        "name": "Overlay"
      },
      "properties": {
        "Content": {
          "type": "ObjectProperty",
          "value": {
            "type": "reference",
            "value": {
              "package": "{{THIS PACKAGE}}",
              "name": "OptionsIconBG"
            }
          }
        },
        "Parent": {
          "type": "ObjectProperty",
          "value": {
            "type": "reference",
            "value": {
              "package": "{{THIS PACKAGE}}",
              "name": "Overlay"
            }
          }
        }
      }
    }
  ]
}