{
  "file_name": "FactoryGame/Content/FactoryGame/World/Environment/Caves/Textures/T_AncientMushrooms_A_ORM.uasset",
  "guid": {
    "a": 2213294652,
    "b": 1149038606,
    "c": 3282004121,
    "d": 2520614432
  },
  "exports": [
    {
      "name": "T_AncientMushrooms_A_ORM",
      "class": {
        "package": "/Script/Engine",
        "name": "Texture2D"
      },
      "super": null,
      "template": {
        "package": "/Script/Engine",
        "name": "Default__Texture2D"
      },
      "outer": null,
      "properties": {
        "CompressionSettings": {
          "type": "ByteProperty",
          "value": "TC_Masks"
        },
        "ImportedSize": {
          "type": "IntPoint",
          "value": {
            "x": 4096,
            "y": 4096
          }
        },
        "LODBias": {
          "type": "IntProperty",
          "value": 2
        },
        "LightingGuid": {
          "type": "Guid",
          "value": {
            "a": 2340142279,
            "b": 1169812439,
            "c": 3850411955,
            "d": 1132063108
          }
        },
        "SRGB": {
          "type": "BoolProperty",
          "value": false
        }
      }
    }
  ]
}