{
  "file_name": "FactoryGame/Content/FactoryGame/-Shared/Blueprint/BP_GameState.uasset",
  "guid": {
    "a": 1127731087,
    "b": 1331555369,
    "c": 3320831155,
    "d": 1657489494
  },
  "exports": [
    {
      "name": "DefaultSceneRoot",
      "class": {
        "package": "/Script/CoreUObject",
        "name": "ObjectProperty"
      },
      "super": null,
      "template": {
        "package": "/Script/CoreUObject",
        "name": "Default__ObjectProperty"
      },
      "outer": {
        "package": "{{THIS PACKAGE}}",
        "name": "BP_GameState_C"
      },
      "properties": {}
    },
    {
      "name": "allRepresentations",
      "class": {
        "package": "/Script/CoreUObject",
        "name": "ArrayProperty"
      },
      "super": null,
      "template": {
        "package": "/Script/CoreUObject",
        "name": "Default__ArrayProperty"
      },
      "outer": {
        "package": "{{THIS PACKAGE}}",
        "name": "DumpActorRepresentations"
      },
      "properties": {}
    },
    {
      "name": "K2Node_Event_DeltaSeconds",
      "class": {
        "package": "/Script/CoreUObject",
        "name": "FloatProperty"
      },
      "super": null,
      "template": {
        "package": "/Script/CoreUObject",
        "name": "Default__FloatProperty"
      },
      "outer": {
        "package": "{{THIS PACKAGE}}",
        "name": "ExecuteUbergraph_BP_GameState"
      },
      "properties": {}
    },
    {
      "name": "CallFunc_GetRealActor_ReturnValue",
      "class": {
        "package": "/Script/CoreUObject",
        "name": "ObjectProperty"
      },
      "super": null,
      "template": {
        "package": "/Script/CoreUObject",
        "name": "Default__ObjectProperty"
      },
      "outer": {
        "package": "{{THIS PACKAGE}}",
        "name": "DumpActorRepresentations"
      },
      "properties": {}
    },
    {
      "name": "CallFunc_Add_IntInt_ReturnValue",
      "class": {
        "package": "/Script/CoreUObject",
        "name": "IntProperty"
      },
      "super": null,
      "template": {
        "package": "/Script/CoreUObject",
        "name": "Default__IntProperty"
      },
      "outer": {
        "package": "{{THIS PACKAGE}}",
        "name": "DumpActorRepresentations"
      },
      "properties": {}
    },
    {
      "name": "CallFunc_Array_Length_ReturnValue",
      "class": {
        "package": "/Script/CoreUObject",
        "name": "IntProperty"
      },
      "super": null,
      "template": {
        "package": "/Script/CoreUObject",
        "name": "Default__IntProperty"
      },
      "outer": {
        "package": "{{THIS PACKAGE}}",
        "name": "DumpVisistedMapAreas"
      },
      "properties": {}
    },
    {
      "name": "Temp_int_Loop_Counter_Variable",
      "class": {
        "package": "/Script/CoreUObject",
        "name": "IntProperty"
      },
      "super": null,
      "template": {
        "package": "/Script/CoreUObject",
        "name": "Default__IntProperty"
      },
      "outer": {
        "package": "{{THIS PACKAGE}}",
        "name": "DumpVisistedMapAreas"
      },
      "properties": {}
    },
    {
      "name": "SCS_Node",
      "class": {
        "package": "/Script/Engine",
        "name": "SCS_Node"
      },
      "super": null,
      "template": {
        "package": "/Script/Engine",
        "name": "Default__SCS_Node"
      },
      "outer": {
        "package": "{{THIS PACKAGE}}",
        "name": "{{BROKEN/MISSING EXPORT}}"
      },
      "properties": {
        "ComponentClass": {
          "type": "ObjectProperty",
          "value": {
            "type": "reference",
            "value": {
              "package": "/Script/Engine",
              "name": "SceneComponent"
            }
          }
        },
        "ComponentTemplate": {
          "type": "ObjectProperty",
          "value": {
            "type": "reference",
            "value": {
              "package": "{{THIS PACKAGE}}",
              "name": "DefaultSceneRoot_GEN_VARIABLE"
            }
          }
        },
        "InternalVariableName": {
          "type": "NameProperty",
          "value": "DefaultSceneRoot"
        },
        "VariableGuid": {
          "type": "Guid",
          "value": {
            "a": 1676756093,
            "b": 1165960597,
            "c": 1215971254,
            "d": 3973506873
          }
        }
      }
    },
    {
      "name": "SimpleConstructionScript",
      "class": {
        "package": "/Script/Engine",
        "name": "SimpleConstructionScript"
      },
      "super": null,
      "template": {
        "package": "/Script/Engine",
        "name": "Default__SimpleConstructionScript"
      },
      "outer": {
        "package": "{{THIS PACKAGE}}",
        "name": "BP_GameState_C"
      },
      "properties": {
        "AllNodes": {
          "type": "ArrayProperty",
          "value": [
            {
              "type": "reference",
              "value": {
                "package": "{{THIS PACKAGE}}",
                "name": "SCS_Node"
              }
            }
          ]
        },
        "DefaultSceneRootNode": {
          "type": "ObjectProperty",
          "value": {
            "type": "reference",
            "value": {
              "package": "{{THIS PACKAGE}}",
              "name": "SCS_Node"
            }
          }
        },
        "RootNodes": {
          "type": "ArrayProperty",
          "value": [
            {
              "type": "reference",
              "value": {
                "package": "{{THIS PACKAGE}}",
                "name": "SCS_Node"
              }
            }
          ]
        }
      }
    },
    {
      "name": "CallFunc_Concat_StrStr_ReturnValue",
      "class": {
        "package": "/Script/CoreUObject",
        "name": "StrProperty"
      },
      "super": null,
      "template": {
        "package": "/Script/CoreUObject",
        "name": "Default__StrProperty"
      },
      "outer": {
        "package": "{{THIS PACKAGE}}",
        "name": "DumpActorRepresentations"
      },
      "properties": {}
    },
    {
      "name": "CallFunc_Conv_IntToString_ReturnValue",
      "class": {
        "package": "/Script/CoreUObject",
        "name": "StrProperty"
      },
      "super": null,
      "template": {
        "package": "/Script/CoreUObject",
        "name": "Default__StrProperty"
      },
      "outer": {
        "package": "{{THIS PACKAGE}}",
        "name": "DumpActorRepresentations"
      },
      "properties": {}
    },
    {
      "name": "CallFunc_GetDisplayName_ReturnValue",
      "class": {
        "package": "/Script/CoreUObject",
        "name": "StrProperty"
      },
      "super": null,
      "template": {
        "package": "/Script/CoreUObject",
        "name": "Default__StrProperty"
      },
      "outer": {
        "package": "{{THIS PACKAGE}}",
        "name": "DumpActorRepresentations"
      },
      "properties": {}
    },
    {
      "name": "Default__BP_GameState_C",
      "class": {
        "package": "{{THIS PACKAGE}}",
        "name": "BP_GameState_C"
      },
      "super": null,
      "template": {
        "package": "/Script/FactoryGame",
        "name": "Default__FGGameState"
      },
      "outer": null,
      "properties": {
        "UberGraphFrame": {
          "type": "PointerToUberGraphFrame",
          "value": null
        },
        "mHubPartClass": {
          "type": "ObjectProperty",
          "value": {
            "type": "reference",
            "value": {
              "package": "/Game/FactoryGame/Resource/Parts/HUBParts/Desc_HUBParts",
              "name": "Desc_HUBParts_C"
            }
          }
        },
        "mPowerCircuitFuseTriggeredMessage": {
          "type": "ObjectProperty",
          "value": {
            "type": "reference",
            "value": {
              "package": "/Game/FactoryGame/Interface/UI/Message/Notification/PowerCircuitFuseTriggered",
              "name": "PowerCircuitFuseTriggered_C"
            }
          }
        },
        "mTurboModeMultiplier": {
          "type": "FloatProperty",
          "value": 8
        }
      }
    },
    {
      "name": "DumpVisistedMapAreas",
      "class": {
        "package": "/Script/CoreUObject",
        "name": "Function"
      },
      "super": null,
      "template": {
        "package": "/Script/CoreUObject",
        "name": "Default__Function"
      },
      "outer": {
        "package": "{{THIS PACKAGE}}",
        "name": "BP_GameState_C"
      },
      "properties": {}
    },
    {
      "name": "mapAreas",
      "class": {
        "package": "/Script/CoreUObject",
        "name": "ArrayProperty"
      },
      "super": null,
      "template": {
        "package": "/Script/CoreUObject",
        "name": "Default__ArrayProperty"
      },
      "outer": {
        "package": "{{THIS PACKAGE}}",
        "name": "DumpVisistedMapAreas"
      },
      "properties": {}
    },
    {
      "name": "CallFunc_Array_Get_Item",
      "class": {
        "package": "/Script/CoreUObject",
        "name": "ClassProperty"
      },
      "super": null,
      "template": {
        "package": "/Script/CoreUObject",
        "name": "Default__ClassProperty"
      },
      "outer": {
        "package": "{{THIS PACKAGE}}",
        "name": "DumpVisistedMapAreas"
      },
      "properties": {}
    },
    {
      "name": "Temp_int_Loop_Counter_Variable",
      "class": {
        "package": "/Script/CoreUObject",
        "name": "IntProperty"
      },
      "super": null,
      "template": {
        "package": "/Script/CoreUObject",
        "name": "Default__IntProperty"
      },
      "outer": {
        "package": "{{THIS PACKAGE}}",
        "name": "DumpActorRepresentations"
      },
      "properties": {}
    },
    {
      "name": "CallFunc_Array_Get_Item",
      "class": {
        "package": "/Script/CoreUObject",
        "name": "ObjectProperty"
      },
      "super": null,
      "template": {
        "package": "/Script/CoreUObject",
        "name": "Default__ObjectProperty"
      },
      "outer": {
        "package": "{{THIS PACKAGE}}",
        "name": "DumpActorRepresentations"
      },
      "properties": {}
    },
    {
      "name": "CallFunc_Concat_StrStr_ReturnValue1",
      "class": {
        "package": "/Script/CoreUObject",
        "name": "StrProperty"
      },
      "super": null,
      "template": {
        "package": "/Script/CoreUObject",
        "name": "Default__StrProperty"
      },
      "outer": {
        "package": "{{THIS PACKAGE}}",
        "name": "DumpActorRepresentations"
      },
      "properties": {}
    },
    {
      "name": "ReceiveTick",
      "class": {
        "package": "/Script/CoreUObject",
        "name": "Function"
      },
      "super": {
        "package": "Actor",
        "name": "ReceiveTick"
      },
      "template": {
        "package": "/Script/CoreUObject",
        "name": "Default__Function"
      },
      "outer": {
        "package": "{{THIS PACKAGE}}",
        "name": "BP_GameState_C"
      },
      "properties": {}
    },
    {
      "name": "DumpActorRepresentations",
      "class": {
        "package": "/Script/CoreUObject",
        "name": "Function"
      },
      "super": null,
      "template": {
        "package": "/Script/CoreUObject",
        "name": "Default__Function"
      },
      "outer": {
        "package": "{{THIS PACKAGE}}",
        "name": "BP_GameState_C"
      },
      "properties": {}
    },
    {
      "name": "CallFunc_Less_IntInt_ReturnValue",
      "class": {
        "package": "/Script/CoreUObject",
        "name": "BoolProperty"
      },
      "super": null,
      "template": {
        "package": "/Script/CoreUObject",
        "name": "Default__BoolProperty"
      },
      "outer": {
        "package": "{{THIS PACKAGE}}",
        "name": "DumpVisistedMapAreas"
      },
      "properties": {}
    },
    {
      "name": "CallFunc_Add_IntInt_ReturnValue",
      "class": {
        "package": "/Script/CoreUObject",
        "name": "IntProperty"
      },
      "super": null,
      "template": {
        "package": "/Script/CoreUObject",
        "name": "Default__IntProperty"
      },
      "outer": {
        "package": "{{THIS PACKAGE}}",
        "name": "DumpVisistedMapAreas"
      },
      "properties": {}
    },
    {
      "name": "DefaultSceneRoot_GEN_VARIABLE",
      "class": {
        "package": "/Script/Engine",
        "name": "SceneComponent"
      },
      "super": null,
      "template": {
        "package": "/Script/Engine",
        "name": "Default__SceneComponent"
      },
      "outer": {
        "package": "{{THIS PACKAGE}}",
        "name": "BP_GameState_C"
      },
      "properties": {}
    },
    {
      "name": "CallFunc_Conv_VectorToString_ReturnValue",
      "class": {
        "package": "/Script/CoreUObject",
        "name": "StrProperty"
      },
      "super": null,
      "template": {
        "package": "/Script/CoreUObject",
        "name": "Default__StrProperty"
      },
      "outer": {
        "package": "{{THIS PACKAGE}}",
        "name": "DumpActorRepresentations"
      },
      "properties": {}
    },
    {
      "name": "CallFunc_Concat_StrStr_ReturnValue",
      "class": {
        "package": "/Script/CoreUObject",
        "name": "StrProperty"
      },
      "super": null,
      "template": {
        "package": "/Script/CoreUObject",
        "name": "Default__StrProperty"
      },
      "outer": {
        "package": "{{THIS PACKAGE}}",
        "name": "DumpVisistedMapAreas"
      },
      "properties": {}
    },
    {
      "name": "CallFunc_GetActorLocation_ReturnValue",
      "class": {
        "package": "/Script/CoreUObject",
        "name": "StructProperty"
      },
      "super": null,
      "template": {
        "package": "/Script/CoreUObject",
        "name": "Default__StructProperty"
      },
      "outer": {
        "package": "{{THIS PACKAGE}}",
        "name": "DumpActorRepresentations"
      },
      "properties": {}
    },
    {
      "name": "CallFunc_GetAreaDisplayName_ReturnValue",
      "class": {
        "package": "/Script/CoreUObject",
        "name": "TextProperty"
      },
      "super": null,
      "template": {
        "package": "/Script/CoreUObject",
        "name": "Default__TextProperty"
      },
      "outer": {
        "package": "{{THIS PACKAGE}}",
        "name": "DumpVisistedMapAreas"
      },
      "properties": {}
    },
    {
      "name": "EntryPoint",
      "class": {
        "package": "/Script/CoreUObject",
        "name": "IntProperty"
      },
      "super": null,
      "template": {
        "package": "/Script/CoreUObject",
        "name": "Default__IntProperty"
      },
      "outer": {
        "package": "{{THIS PACKAGE}}",
        "name": "{{BROKEN/MISSING EXPORT}}"
      },
      "properties": {}
    },
    {
      "name": "DeltaSeconds",
      "class": {
        "package": "/Script/CoreUObject",
        "name": "FloatProperty"
      },
      "super": null,
      "template": {
        "package": "/Script/CoreUObject",
        "name": "Default__FloatProperty"
      },
      "outer": {
        "package": "{{THIS PACKAGE}}",
        "name": "{{BROKEN/MISSING EXPORT}}"
      },
      "properties": {}
    },
    {
      "name": "mapAreas",
      "class": {
        "package": "/Script/CoreUObject",
        "name": "ClassProperty"
      },
      "super": null,
      "template": {
        "package": "/Script/CoreUObject",
        "name": "Default__ClassProperty"
      },
      "outer": {
        "package": "{{THIS PACKAGE}}",
        "name": "{{BROKEN/MISSING EXPORT}}"
      },
      "properties": {}
    },
    {
      "name": "Temp_int_Array_Index_Variable",
      "class": {
        "package": "/Script/CoreUObject",
        "name": "IntProperty"
      },
      "super": null,
      "template": {
        "package": "/Script/CoreUObject",
        "name": "Default__IntProperty"
      },
      "outer": {
        "package": "{{THIS PACKAGE}}",
        "name": "DumpVisistedMapAreas"
      },
      "properties": {}
    },
    {
      "name": "CallFunc_GetPlayerController_ReturnValue",
      "class": {
        "package": "/Script/CoreUObject",
        "name": "ObjectProperty"
      },
      "super": null,
      "template": {
        "package": "/Script/CoreUObject",
        "name": "Default__ObjectProperty"
      },
      "outer": {
        "package": "{{THIS PACKAGE}}",
        "name": "DumpVisistedMapAreas"
      },
      "properties": {}
    },
    {
      "name": "CallFunc_GetAreaDisplayName_ReturnValue1",
      "class": {
        "package": "/Script/CoreUObject",
        "name": "TextProperty"
      },
      "super": null,
      "template": {
        "package": "/Script/CoreUObject",
        "name": "Default__TextProperty"
      },
      "outer": {
        "package": "{{THIS PACKAGE}}",
        "name": "DumpVisistedMapAreas"
      },
      "properties": {}
    },
    {
      "name": "BP_GameState_C",
      "class": {
        "package": "/Script/Engine",
        "name": "BlueprintGeneratedClass"
      },
      "super": {
        "package": "/Script/FactoryGame",
        "name": "FGGameState"
      },
      "template": {
        "package": "/Script/Engine",
        "name": "Default__BlueprintGeneratedClass"
      },
      "outer": null,
      "properties": {
        "SimpleConstructionScript": {
          "type": "ObjectProperty",
          "value": {
            "type": "reference",
            "value": {
              "package": "{{THIS PACKAGE}}",
              "name": "SimpleConstructionScript"
            }
          }
        },
        "UberGraphFramePointerProperty": {
          "type": "ObjectProperty",
          "value": {
            "type": "reference",
            "value": {
              "package": "{{THIS PACKAGE}}",
              "name": "UberGraphFrame"
            }
          }
        },
        "UberGraphFunction": {
          "type": "ObjectProperty",
          "value": {
            "type": "reference",
            "value": {
              "package": "{{THIS PACKAGE}}",
              "name": "ExecuteUbergraph_BP_GameState"
            }
          }
        }
      }
    },
    {
      "name": "allRepresentations",
      "class": {
        "package": "/Script/CoreUObject",
        "name": "ObjectProperty"
      },
      "super": null,
      "template": {
        "package": "/Script/CoreUObject",
        "name": "Default__ObjectProperty"
      },
      "outer": {
        "package": "{{THIS PACKAGE}}",
        "name": "{{BROKEN/MISSING EXPORT}}"
      },
      "properties": {}
    },
    {
      "name": "K2Node_DynamicCast_bSuccess",
      "class": {
        "package": "/Script/CoreUObject",
        "name": "BoolProperty"
      },
      "super": null,
      "template": {
        "package": "/Script/CoreUObject",
        "name": "Default__BoolProperty"
      },
      "outer": {
        "package": "{{THIS PACKAGE}}",
        "name": "DumpVisistedMapAreas"
      },
      "properties": {}
    },
    {
      "name": "CallFunc_Concat_StrStr_ReturnValue3",
      "class": {
        "package": "/Script/CoreUObject",
        "name": "StrProperty"
      },
      "super": null,
      "template": {
        "package": "/Script/CoreUObject",
        "name": "Default__StrProperty"
      },
      "outer": {
        "package": "{{THIS PACKAGE}}",
        "name": "DumpActorRepresentations"
      },
      "properties": {}
    },
    {
      "name": "CallFunc_Conv_TextToString_ReturnValue",
      "class": {
        "package": "/Script/CoreUObject",
        "name": "StrProperty"
      },
      "super": null,
      "template": {
        "package": "/Script/CoreUObject",
        "name": "Default__StrProperty"
      },
      "outer": {
        "package": "{{THIS PACKAGE}}",
        "name": "DumpVisistedMapAreas"
      },
      "properties": {}
    },
    {
      "name": "CallFunc_Less_IntInt_ReturnValue",
      "class": {
        "package": "/Script/CoreUObject",
        "name": "BoolProperty"
      },
      "super": null,
      "template": {
        "package": "/Script/CoreUObject",
        "name": "Default__BoolProperty"
      },
      "outer": {
        "package": "{{THIS PACKAGE}}",
        "name": "DumpActorRepresentations"
      },
      "properties": {}
    },
    {
      "name": "CallFunc_GetCurrentMapArea_ReturnValue",
      "class": {
        "package": "/Script/CoreUObject",
        "name": "ClassProperty"
      },
      "super": null,
      "template": {
        "package": "/Script/CoreUObject",
        "name": "Default__ClassProperty"
      },
      "outer": {
        "package": "{{THIS PACKAGE}}",
        "name": "DumpVisistedMapAreas"
      },
      "properties": {}
    },
    {
      "name": "Temp_int_Array_Index_Variable",
      "class": {
        "package": "/Script/CoreUObject",
        "name": "IntProperty"
      },
      "super": null,
      "template": {
        "package": "/Script/CoreUObject",
        "name": "Default__IntProperty"
      },
      "outer": {
        "package": "{{THIS PACKAGE}}",
        "name": "DumpActorRepresentations"
      },
      "properties": {}
    },
    {
      "name": "K2Node_DynamicCast_AsFGPlayer_Controller",
      "class": {
        "package": "/Script/CoreUObject",
        "name": "ObjectProperty"
      },
      "super": null,
      "template": {
        "package": "/Script/CoreUObject",
        "name": "Default__ObjectProperty"
      },
      "outer": {
        "package": "{{THIS PACKAGE}}",
        "name": "DumpVisistedMapAreas"
      },
      "properties": {}
    },
    {
      "name": "CallFunc_Conv_TextToString_ReturnValue1",
      "class": {
        "package": "/Script/CoreUObject",
        "name": "StrProperty"
      },
      "super": null,
      "template": {
        "package": "/Script/CoreUObject",
        "name": "Default__StrProperty"
      },
      "outer": {
        "package": "{{THIS PACKAGE}}",
        "name": "DumpVisistedMapAreas"
      },
      "properties": {}
    },
    {
      "name": "UberGraphFrame",
      "class": {
        "package": "/Script/CoreUObject",
        "name": "StructProperty"
      },
      "super": null,
      "template": {
        "package": "/Script/CoreUObject",
        "name": "Default__StructProperty"
      },
      "outer": {
        "package": "{{THIS PACKAGE}}",
        "name": "{{BROKEN/MISSING EXPORT}}"
      },
      "properties": {}
    },
    {
      "name": "ExecuteUbergraph_BP_GameState",
      "class": {
        "package": "/Script/CoreUObject",
        "name": "Function"
      },
      "super": null,
      "template": {
        "package": "/Script/CoreUObject",
        "name": "Default__Function"
      },
      "outer": {
        "package": "{{THIS PACKAGE}}",
        "name": "BP_GameState_C"
      },
      "properties": {}
    },
    {
      "name": "CallFunc_Array_Length_ReturnValue",
      "class": {
        "package": "/Script/CoreUObject",
        "name": "IntProperty"
      },
      "super": null,
      "template": {
        "package": "/Script/CoreUObject",
        "name": "Default__IntProperty"
      },
      "outer": {
        "package": "{{THIS PACKAGE}}",
        "name": "DumpActorRepresentations"
      },
      "properties": {}
    },
    {
      "name": "CallFunc_Get_ReturnValue",
      "class": {
        "package": "/Script/CoreUObject",
        "name": "ObjectProperty"
      },
      "super": null,
      "template": {
        "package": "/Script/CoreUObject",
        "name": "Default__ObjectProperty"
      },
      "outer": {
        "package": "{{THIS PACKAGE}}",
        "name": "DumpActorRepresentations"
      },
      "properties": {}
    },
    {
      "name": "CallFunc_Concat_StrStr_ReturnValue2",
      "class": {
        "package": "/Script/CoreUObject",
        "name": "StrProperty"
      },
      "super": null,
      "template": {
        "package": "/Script/CoreUObject",
        "name": "Default__StrProperty"
      },
      "outer": {
        "package": "{{THIS PACKAGE}}",
        "name": "DumpActorRepresentations"
      },
      "properties": {}
    }
  ]
}