{
  "file_name": "FactoryGame/Content/FactoryGame/Buildable/Factory/GeneratorGeoThermal/Audio/Stop_GeoThermal_Turbine_Loop.uasset",
  "guid": {
    "a": 4026974092,
    "b": 1107830787,
    "c": 2409435049,
    "d": 3216867905
  },
  "exports": [
    {
      "name": "Stop_GeoThermal_Turbine_Loop",
      "class": {
        "package": "/Script/AkAudio",
        "name": "AkAudioEvent"
      },
      "super": null,
      "template": {
        "package": "/Script/AkAudio",
        "name": "Default__AkAudioEvent"
      },
      "outer": null,
      "properties": {
        "RequiredBank": {
          "type": "ObjectProperty",
          "value": {
            "type": "reference",
            "value": {
              "package": "/Game/FactoryGame/Buildable/Factory/GeneratorGeoThermal/Audio/Factory_Generator_GeoThermal",
              "name": "Factory_Generator_GeoThermal"
            }
          }
        }
      }
    }
  ]
}